Workbook

Sheet How to use
B1: Cortex Cloud upgrade: field assessment tracker
B3: What this tracker answers for each account
B4: 1) Which technical blockers the customer has confirmed. 2) Which of those have no committed release date. 3) Which release clears the account, and the expected start date.
B6: How to fill it in
B7: 1. Accounts tab: one row per account. Fill the white columns. Set Assessment status to Complete only when every relevant gap has been validated with the customer.
B8: 2. Blocker log tab: one row per gap discussed with the customer. Pick the account and gap from the dropdowns; release, default view and PM owner fill in automatically. This is for Roadmap blocking items only (Parity and Top 100 Account Feature Requests)
B9: 3. Set Customer outcome: Hard blocker, Workaround accepted, Not needed or Unknown. For a blocker that is not on the gap list, pick 'Other (not on gap list)' and describe it.
B10: 4. Record whether telemetry matched what the customer told you. These corrections improve telemetry for the next wave of accounts.
B11: 5. Playbook feedback tab: anything we should change in the runbook, telemetry or product.
B13: How the readiness bucket is set (automatic)
B14: Ready now: no validated hard blockers. Otherwise the latest planned release among the account's hard blockers sets the bucket.
B15: No date: at least one hard blocker has No date, TBC, Not planned or Unknown. These rows show Escalate = Yes in the Blocker log; raise them with the PM owner.
... B21: The full approach is in the TSE Field Assessment Guide.

Sheet Summary
A1: Field assessment summary
A2: All figures update from the Accounts and Blocker log tabs. Grey cells are formulas; do not type over them.
A4: Coverage
A5: Accounts in scope | B5: =COUNTA(Accounts!$B:$B) -> 1368
A6: Assessments complete | B6: =COUNTIF(Accounts!$K$2:$K$161,"Complete") -> 15
A7: % complete | B7: =IF(B5=0,0,B6/B5) -> 0.010964912
A9: Readiness buckets (completed assessments)
A10: Bucket | B10: # accounts | C10: ARR ($M) | D10: % of complete
A11: Ready now | B11: =COUNTIF(Accounts!$Q:$Q,$A11) -> 15 | C11: =SUMIFS(Accounts!$H:$H,Accounts!$Q:$Q,$A11) -> 22194564 | D11: =IF($B$6=0,0,B11/$B$6) -> 1
A12: After October release | B12: =COUNTIF(Accounts!$Q:$Q,$A12) -> 0 | C12: =SUMIFS(Accounts!$H:$H,Accounts!$Q:$Q,$A12) -> 0 | D12: =IF($B$6=0,0,B12/$B$6) -> 0
A13: After January release | B13: =COUNTIF(Accounts!$Q:$Q,$A13) -> 0 | C13: =SUMIFS(Accounts!$H:$H,Accounts!$Q:$Q,$A13) -> 0 | D13: =IF($B$6=0,0,B13/$B$6) -> 0
A14: After April release or later | B14: =COUNTIF(Accounts!$Q:$Q,$A14) -> 0 | C14: =SUMIFS(Accounts!$H:$H,Accounts!$Q:$Q,$A14) -> 0 | D14: =IF($B$6=0,0,B14/$B$6) -> 0
A15: No date | B15: =COUNTIF(Accounts!$Q:$Q,$A15) -> 0 | C15: =SUMIFS(Accounts!$H:$H,Accounts!$Q:$Q,$A15) -> 0 | D15: =IF($B$6=0,0,B15/$B$6) -> 0
A16: Assessment pending | B16: =COUNTIF(Accounts!$Q:$Q,$A16) -> 1351 | C16: =SUMIFS(Accounts!$H:$H,Accounts!$Q:$Q,$A16) -> 265893694
A18: Blockers
A19: Validated hard blockers (all accounts) | B19: =COUNTIF('Blocker log'!$G:$G,"Hard blocker") -> 12
A20: Hard blockers with no committed date | B20: =COUNTIF('Blocker log'!$M:$M,"Yes") -> 0
A21: Accounts with a no-date hard blocker | B21: =COUNTIF(Accounts!$O$2:$O$161,">0") -> 0
A22: Workarounds accepted | B22: =COUNTIF('Blocker log'!$G:$G,"Workaround accepted") -> 5
A23: Blockers not on the gap list | B23: =COUNTIFS('Blocker log'!$B:$B,"Other (not on gap list)",'Blocker log'!$G:$G,"Hard blocker") -> 0
A24: Telemetry mismatches found | B24: =COUNTIF('Blocker log'!$J:$J,"No, *") -> 2
A26: Most common hard blockers: sort the Gap reference tab by its last column.

Sheet Accounts
A1: Account iD | B1: Account | C1: Tier | D1: Theatre | G1: Upgrade status | H1: ARR ($M) | I1: TSE | J1: Companion (ride-along) | K1: Assessment status | L1: Assessment date | M1: # gaps validated | N1: # hard blockers | O1: # hard blockers with no date | P1: Latest release rank | Q1: Readiness bucket | R1: Expected start date | S1: Next step | T1: Escalation reason | U1: Notes
A2: 0017000000qySjdAAE | B2: Cognizant Technology Solutions Corporation | C2: Tier 1 | D2: AMER | E2: AMER Strategic East | F2: AMER Strategic East SI/SP | G2: Cohort 1: Upgrades in progress | H2: 3387281 | I2: Alan Simpkins | K2: Complete | L2: 46315 | M2: =IF($B2="","",COUNTIFS('Blocker log'!$A:$A,$B2,'Blocker log'!$G:$G,"<>")) -> 0 | N2: =IF($B2="","",COUNTIFS('Blocker log'!$A:$A,$B2,'Blocker log'!$G:$G,"Hard blocker")) -> 0 | O2: =IF($B2="","",COUNTIFS('Blocker log'!$A:$A,$B2,'Blocker log'!$G:$G,"Hard blocker",'Blocker log'!$L:$L,9)) -> 0 | P2: =IF($B2="","",MAXIFS('Blocker log'!$L:$L,'Blocker log'!$A:$A,$B2,'Blocker log'!$G:$G,"Hard blocker")) -> 0 | Q2: =IF($B2="","",IF($K2<>"Complete","Assessment pending",IF($N2=0,"Ready now",VLOOKUP($P2,Lists!$D$2:$E$5,2,FALSE)))) -> Ready now
A3: 0017000000WRcO6AAL | B3: HARTFORD FIRE INSURANCE COMPANY | C3: Tier 2 | D3: AMER | E3: AMER Strategic East | F3: AMER Strategic East Northeast | G3: Cohort 1: Upgrades in progress | H3: 333600 | I3: Alan Simpkins | K3: Pending | M3: =IF($B3="","",COUNTIFS('Blocker log'!$A:$A,$B3,'Blocker log'!$G:$G,"<>")) -> 0 | N3: =IF($B3="","",COUNTIFS('Blocker log'!$A:$A,$B3,'Blocker log'!$G:$G,"Hard blocker")) -> 0 | O3: =IF($B3="","",COUNTIFS('Blocker log'!$A:$A,$B3,'Blocker log'!$G:$G,"Hard blocker",'Blocker log'!$L:$L,9)) -> 0 | P3: =IF($B3="","",MAXIFS('Blocker log'!$L:$L,'Blocker log'!$A:$A,$B3,'Blocker log'!$G:$G,"Hard blocker")) -> 0 | Q3: =IF($B3="","",IF($K3<>"Complete","Assessment pending",IF($N3=0,"Ready now",VLOOKUP($P3,Lists!$D$2:$E$5,2,FALSE)))) -> Assessment pending
A4: 0017000000LKb1aAAD | B4: Connection | C4: Tier 2 | D4: AMER | E4: AMER Acquisition | F4: AMER Acquisition | G4: Cohort 1: Upgrades in progress | H4: 33192 | I4: Alan Simpkins | K4: Pending | M4: =IF($B4="","",COUNTIFS('Blocker log'!$A:$A,$B4,'Blocker log'!$G:$G,"<>")) -> 0 | N4: =IF($B4="","",COUNTIFS('Blocker log'!$A:$A,$B4,'Blocker log'!$G:$G,"Hard blocker")) -> 0 | O4: =IF($B4="","",COUNTIFS('Blocker log'!$A:$A,$B4,'Blocker log'!$G:$G,"Hard blocker",'Blocker log'!$L:$L,9)) -> 0 | P4: =IF($B4="","",MAXIFS('Blocker log'!$L:$L,'Blocker log'!$A:$A,$B4,'Blocker log'!$G:$G,"Hard blocker")) -> 0 | Q4: =IF($B4="","",IF($K4<>"Complete","Assessment pending",IF($N4=0,"Ready now",VLOOKUP($P4,Lists!$D$2:$E$5,2,FALSE)))) -> Assessment pending
A5: 0017000000Wc7W0AAJ | B5: ISO New England Inc. | C5: Tier 2 | D5: AMER | E5: AMER Commercial | F5: Select East | G5: Cohort 1: Upgrades in progress | H5: 123584 | I5: Alan Simpkins | K5: Pending | M5: =IF($B5="","",COUNTIFS('Blocker log'!$A:$A,$B5,'Blocker log'!$G:$G,"<>")) -> 0 | N5: =IF($B5="","",COUNTIFS('Blocker log'!$A:$A,$B5,'Blocker log'!$G:$G,"Hard blocker")) -> 0 | O5: =IF($B5="","",COUNTIFS('Blocker log'!$A:$A,$B5,'Blocker log'!$G:$G,"Hard blocker",'Blocker log'!$L:$L,9)) -> 0 | P5: =IF($B5="","",MAXIFS('Blocker log'!$L:$L,'Blocker log'!$A:$A,$B5,'Blocker log'!$G:$G,"Hard blocker")) -> 0 | Q5: =IF($B5="","",IF($K5<>"Complete","Assessment pending",IF($N5=0,"Ready now",VLOOKUP($P5,Lists!$D$2:$E$5,2,FALSE)))) -> Assessment pending
A6: 0017000000rXvEBAA0 | B6: Skillsoft Corporation | C6: Tier 2 | D6: AMER | E6: AMER Commercial | F6: Select West | G6: Cohort 1: Upgrades in progress | H6: 112962 | I6: Alan Simpkins | K6: Pending | M6: =IF($B6="","",COUNTIFS('Blocker log'!$A:$A,$B6,'Blocker log'!$G:$G,"<>")) -> 0 | N6: =IF($B6="","",COUNTIFS('Blocker log'!$A:$A,$B6,'Blocker log'!$G:$G,"Hard blocker")) -> 0 | O6: =IF($B6="","",COUNTIFS('Blocker log'!$A:$A,$B6,'Blocker log'!$G:$G,"Hard blocker",'Blocker log'!$L:$L,9)) -> 0 | P6: =IF($B6="","",MAXIFS('Blocker log'!$L:$L,'Blocker log'!$A:$A,$B6,'Blocker log'!$G:$G,"Hard blocker")) -> 0 | Q6: =IF($B6="","",IF($K6<>"Complete","Assessment pending",IF($N6=0,"Ready now",VLOOKUP($P6,Lists!$D$2:$E$5,2,FALSE)))) -> Assessment pending
A7: 0017000000jurAfAAI | B7: MetLife, Inc. | C7: Tier 1 | D7: AMER | E7: AMER Strategic East | F7: AMER Strategic East FIS | G7: Cohort 1: Upgrades in progress | H7: 2191200 | I7: Alex Reshetniak | K7: Complete | L7: 46316 | M7: =IF($B7="","",COUNTIFS('Blocker log'!$A:$A,$B7,'Blocker log'!$G:$G,"<>")) -> 0 | N7: =IF($B7="","",COUNTIFS('Blocker log'!$A:$A,$B7,'Blocker log'!$G:$G,"Hard blocker")) -> 0 | O7: =IF($B7="","",COUNTIFS('Blocker log'!$A:$A,$B7,'Blocker log'!$G:$G,"Hard blocker",'Blocker log'!$L:$L,9)) -> 0 | P7: =IF($B7="","",MAXIFS('Blocker log'!$L:$L,'Blocker log'!$A:$A,$B7,'Blocker log'!$G:$G,"Hard blocker")) -> 0 | Q7: =IF($B7="","",IF($K7<>"Complete","Assessment pending",IF($N7=0,"Ready now",VLOOKUP($P7,Lists!$D$2:$E$5,2,FALSE)))) -> Ready now
A8: 0014u00002BGospAAD | B8: Fed-Tulip38 | C8: Tier 1 | D8: AMER | E8: US Public Sector | F8: SLED Northeast | G8: Cohort 1: Upgrades in progress | H8: 2415715 | M8: =IF($B8="","",COUNTIFS('Blocker log'!$A:$A,$B8,'Blocker log'!$G:$G,"<>")) -> 0 | N8: =IF($B8="","",COUNTIFS('Blocker log'!$A:$A,$B8,'Blocker log'!$G:$G,"Hard blocker")) -> 0 | O8: =IF($B8="","",COUNTIFS('Blocker log'!$A:$A,$B8,'Blocker log'!$G:$G,"Hard blocker",'Blocker log'!$L:$L,9)) -> 0 | P8: =IF($B8="","",MAXIFS('Blocker log'!$L:$L,'Blocker log'!$A:$A,$B8,'Blocker log'!$G:$G,"Hard blocker")) -> 0 | Q8: =IF($B8="","",IF($K8<>"Complete","Assessment pending",IF($N8=0,"Ready now",VLOOKUP($P8,Lists!$D$2:$E$5,2,FALSE)))) -> Assessment pending
A9: 0017000000bFPu8AAG | B9: Equinix, Inc. | C9: Tier 1 | D9: AMER | E9: AMER Strategic West | F9: AMER Strategic West NorCal | G9: Cohort 1: Upgrades in progress | H9: 955532 | I9: Alex Reshetniak | K9: Complete | L9: 46316 | M9: =IF($B9="","",COUNTIFS('Blocker log'!$A:$A,$B9,'Blocker log'!$G:$G,"<>")) -> 0 | N9: =IF($B9="","",COUNTIFS('Blocker log'!$A:$A,$B9,'Blocker log'!$G:$G,"Hard blocker")) -> 0 | O9: =IF($B9="","",COUNTIFS('Blocker log'!$A:$A,$B9,'Blocker log'!$G:$G,"Hard blocker",'Blocker log'!$L:$L,9)) -> 0 | P9: =IF($B9="","",MAXIFS('Blocker log'!$L:$L,'Blocker log'!$A:$A,$B9,'Blocker log'!$G:$G,"Hard blocker")) -> 0 | Q9: =IF($B9="","",IF($K9<>"Complete","Assessment pending",IF($N9=0,"Ready now",VLOOKUP($P9,Lists!$D$2:$E$5,2,FALSE)))) -> Ready now
A10: 0017000000drDq2AAE | B10: Intrado Life & Safety | C10: Tier 2 | D10: AMER | E10: AMER Commercial | F10: Select West | G10: Cohort 1: Upgrades in progress | H10: 376301 | I10: Alex Reshetniak | K10: Complete | L10: 46316 | M10: =IF($B10="","",COUNTIFS('Blocker log'!$A:$A,$B10,'Blocker log'!$G:$G,"<>")) -> 0 | N10: =IF($B10="","",COUNTIFS('Blocker log'!$A:$A,$B10,'Blocker log'!$G:$G,"Hard blocker")) -> 0 | O10: =IF($B10="","",COUNTIFS('Blocker log'!$A:$A,$B10,'Blocker log'!$G:$G,"Hard blocker",'Blocker log'!$L:$L,9)) -> 0 | P10: =IF($B10="","",MAXIFS('Blocker log'!$L:$L,'Blocker log'!$A:$A,$B10,'Blocker log'!$G:$G,"Hard blocker")) -> 0 | Q10: =IF($B10="","",IF($K10<>"Complete","Assessment pending",IF($N10=0,"Ready now",VLOOKUP($P10,Lists!$D$2:$E$5,2,FALSE)))) -> Ready now
A11: 0017000000wKwTRAA0 | B11: Allegiant Travel Company | C11: Tier 2 | D11: AMER | E11: AMER Strategic West | F11: AMER Strategic West MTN | G11: Cohort 1: Upgrades in progress | H11: 210260 | I11: Alex Reshetniak | K11: Complete | L11: 46316 | M11: =IF($B11="","",COUNTIFS('Blocker log'!$A:$A,$B11,'Blocker log'!$G:$G,"<>")) -> 0 | N11: =IF($B11="","",COUNTIFS('Blocker log'!$A:$A,$B11,'Blocker log'!$G:$G,"Hard blocker")) -> 0 | O11: =IF($B11="","",COUNTIFS('Blocker log'!$A:$A,$B11,'Blocker log'!$G:$G,"Hard blocker",'Blocker log'!$L:$L,9)) -> 0 | P11: =IF($B11="","",MAXIFS('Blocker log'!$L:$L,'Blocker log'!$A:$A,$B11,'Blocker log'!$G:$G,"Hard blocker")) -> 0 | Q11: =IF($B11="","",IF($K11<>"Complete","Assessment pending",IF($N11=0,"Ready now",VLOOKUP($P11,Lists!$D$2:$E$5,2,FALSE)))) -> Ready now
A12: 0017000001NUIVSAA5 | B12: Personal Capital Corporation | C12: Tier 2 | D12: AMER | E12: AMER Strategic West | F12: AMER Strategic West MTN | G12: Cohort 1: Upgrades in progress | H12: 189000 | I12: Alex Reshetniak | K12: Complete | L12: 46316 | M12: =IF($B12="","",COUNTIFS('Blocker log'!$A:$A,$B12,'Blocker log'!$G:$G,"<>")) -> 0 | N12: =IF($B12="","",COUNTIFS('Blocker log'!$A:$A,$B12,'Blocker log'!$G:$G,"Hard blocker")) -> 0 | O12: =IF($B12="","",COUNTIFS('Blocker log'!$A:$A,$B12,'Blocker log'!$G:$G,"Hard blocker",'Blocker log'!$L:$L,9)) -> 0 | P12: =IF($B12="","",MAXIFS('Blocker log'!$L:$L,'Blocker log'!$A:$A,$B12,'Blocker log'!$G:$G,"Hard blocker")) -> 0 | Q12: =IF($B12="","",IF($K12<>"Complete","Assessment pending",IF($N12=0,"Ready now",VLOOKUP($P12,Lists!$D$2:$E$5,2,FALSE)))) -> Ready now
A13: 0017000000jFWBeAAO | B13: Novo Nordisk A/S | C13: Tier 1 | D13: EMEA | E13: Nordics | F13: Denmark | G13: Cohort 1: Upgrades in progress | H13: 1131332 | I13: Amir Chamma | K13: Pending | M13: =IF($B13="","",COUNTIFS('Blocker log'!$A:$A,$B13,'Blocker log'!$G:$G,"<>")) -> 0 | N13: 0 | O13: =IF($B13="","",COUNTIFS('Blocker log'!$A:$A,$B13,'Blocker log'!$G:$G,"Hard blocker",'Blocker log'!$L:$L,9)) -> 0 | P13: =IF($B13="","",MAXIFS('Blocker log'!$L:$L,'Blocker log'!$A:$A,$B13,'Blocker log'!$G:$G,"Hard blocker")) -> 0 | Q13: =IF($B13="","",IF($K13<>"Complete","Assessment pending",IF($N13=0,"Ready now",VLOOKUP($P13,Lists!$D$2:$E$5,2,FALSE)))) -> Assessment pending
A14: 0017000000neSduAAE | B14: Ulta Salon, Cosmetics & Fragrance, Inc | C14: Tier 2 | D14: AMER | E14: AMER Strategic Central | F14: AMER Strategic Central Northcentral | G14: Cohort 1: Upgrades in progress | H14: 638281 | I14: Brian Lewis | K14: Complete | L14: 46315 | M14: =IF($B14="","",COUNTIFS('Blocker log'!$A:$A,$B14,'Blocker log'!$G:$G,"<>")) -> 0 | N14: =IF($B14="","",COUNTIFS('Blocker log'!$A:$A,$B14,'Blocker log'!$G:$G,"Hard blocker")) -> 0 | O14: =IF($B14="","",COUNTIFS('Blocker log'!$A:$A,$B14,'Blocker log'!$G:$G,"Hard blocker",'Blocker log'!$L:$L,9)) -> 0 | P14: =IF($B14="","",MAXIFS('Blocker log'!$L:$L,'Blocker log'!$A:$A,$B14,'Blocker log'!$G:$G,"Hard blocker")) -> 0 | Q14: =IF($B14="","",IF($K14<>"Complete","Assessment pending",IF($N14=0,"Ready now",VLOOKUP($P14,Lists!$D$2:$E$5,2,FALSE)))) -> Ready now
A15: 0017000000lAllhAAC | B15: Cardinal Health, Inc. | C15: Tier 2 | D15: AMER | E15: AMER Strategic Central | F15: AMER Strategic Central Ohio Valley | G15: Cohort 1: Upgrades in progress | H15: 379749 | I15: Brian Lewis | K15: Complete | L15: 46315 | M15: =IF($B15="","",COUNTIFS('Blocker log'!$A:$A,$B15,'Blocker log'!$G:$G,"<>")) -> 0 | N15: =IF($B15="","",COUNTIFS('Blocker log'!$A:$A,$B15,'Blocker log'!$G:$G,"Hard blocker")) -> 0 | O15: =IF($B15="","",COUNTIFS('Blocker log'!$A:$A,$B15,'Blocker log'!$G:$G,"Hard blocker",'Blocker log'!$L:$L,9)) -> 0 | P15: =IF($B15="","",MAXIFS('Blocker log'!$L:$L,'Blocker log'!$A:$A,$B15,'Blocker log'!$G:$G,"Hard blocker")) -> 0 | Q15: =IF($B15="","",IF($K15<>"Complete","Assessment pending",IF($N15=0,"Ready now",VLOOKUP($P15,Lists!$D$2:$E$5,2,FALSE)))) -> Ready now
A16: 0017000000cKVeuAAG | B16: HealthPartners, Inc. | C16: Tier 2 | D16: AMER | E16: AMER Strategic West | F16: AMER Strategic West Healthcare West | G16: Cohort 1: Upgrades in progress | H16: 144767 | I16: Brian Lewis | K16: Complete | L16: 46315 | M16: =IF($B16="","",COUNTIFS('Blocker log'!$A:$A,$B16,'Blocker log'!$G:$G,"<>")) -> 0 | N16: =IF($B16="","",COUNTIFS('Blocker log'!$A:$A,$B16,'Blocker log'!$G:$G,"Hard blocker")) -> 0 | O16: =IF($B16="","",COUNTIFS('Blocker log'!$A:$A,$B16,'Blocker log'!$G:$G,"Hard blocker",'Blocker log'!$L:$L,9)) -> 0 | P16: =IF($B16="","",MAXIFS('Blocker log'!$L:$L,'Blocker log'!$A:$A,$B16,'Blocker log'!$G:$G,"Hard blocker")) -> 0 | Q16: =IF($B16="","",IF($K16<>"Complete","Assessment pending",IF($N16=0,"Ready now",VLOOKUP($P16,Lists!$D$2:$E$5,2,FALSE)))) -> Ready now
A17: 0017000000oqq3JAAQ | B17: Engie | C17: Tier 1 | D17: EMEA | E17: France | F17: France Strategic | G17: Cohort 1: Upgrades in progress | H17: 1602702 | I17: Christopher Ley | K17: Pending | M17: =IF($B17="","",COUNTIFS('Blocker log'!$A:$A,$B17,'Blocker log'!$G:$G,"<>")) -> 0 | N17: =IF($B17="","",COUNTIFS('Blocker log'!$A:$A,$B17,'Blocker log'!$G:$G,"Hard blocker")) -> 0 | O17: =IF($B17="","",COUNTIFS('Blocker log'!$A:$A,$B17,'Blocker log'!$G:$G,"Hard blocker",'Blocker log'!$L:$L,9)) -> 0 | P17: =IF($B17="","",MAXIFS('Blocker log'!$L:$L,'Blocker log'!$A:$A,$B17,'Blocker log'!$G:$G,"Hard blocker")) -> 0 | Q17: =IF($B17="","",IF($K17<>"Complete","Assessment pending",IF($N17=0,"Ready now",VLOOKUP($P17,Lists!$D$2:$E$5,2,FALSE)))) -> Assessment pending
A18: 0017000001VuycpAAB | B18: Airbus 1 | C18: Tier 1 | D18: EMEA | E18: France | F18: France Strategic | G18: Cohort 1: Upgrades in progress | H18: 467026 | I18: Daniel Tor | K18: Pending | M18: =IF($B18="","",COUNTIFS('Blocker log'!$A:$A,$B18,'Blocker log'!$G:$G,"<>")) -> 0 | N18: =IF($B18="","",COUNTIFS('Blocker log'!$A:$A,$B18,'Blocker log'!$G:$G,"Hard blocker")) -> 0 | O18: =IF($B18="","",COUNTIFS('Blocker log'!$A:$A,$B18,'Blocker log'!$G:$G,"Hard blocker",'Blocker log'!$L:$L,9)) -> 0 | P18: =IF($B18="","",MAXIFS('Blocker log'!$L:$L,'Blocker log'!$A:$A,$B18,'Blocker log'!$G:$G,"Hard blocker")) -> 0 | Q18: =IF($B18="","",IF($K18<>"Complete","Assessment pending",IF($N18=0,"Ready now",VLOOKUP($P18,Lists!$D$2:$E$5,2,FALSE)))) -> Assessment pending
A19: 0017000000rZ0dmAAC | B19: Sabre GLBL Inc | C19: Tier 1 | D19: AMER | E19: AMER Strategic Central | F19: AMER Strategic Central Texas | G19: Cohort 1: Upgrades in progress | H19: 1751558 | I19: Farooq Abrahem | K19: Pending | M19: =IF($B19="","",COUNTIFS('Blocker log'!$A:$A,$B19,'Blocker log'!$G:$G,"<>")) -> 0 | N19: =IF($B19="","",COUNTIFS('Blocker log'!$A:$A,$B19,'Blocker log'!$G:$G,"Hard blocker")) -> 0 | O19: =IF($B19="","",COUNTIFS('Blocker log'!$A:$A,$B19,'Blocker log'!$G:$G,"Hard blocker",'Blocker log'!$L:$L,9)) -> 0 | P19: =IF($B19="","",MAXIFS('Blocker log'!$L:$L,'Blocker log'!$A:$A,$B19,'Blocker log'!$G:$G,"Hard blocker")) -> 0 | Q19: =IF($B19="","",IF($K19<>"Complete","Assessment pending",IF($N19=0,"Ready now",VLOOKUP($P19,Lists!$D$2:$E$5,2,FALSE)))) -> Assessment pending
A20: 0017000000bF5EOAA0 | B20: The NASDAQ OMX Group, Inc. | C20: Tier 1 | D20: AMER | E20: AMER Strategic East | F20: AMER Strategic East NY Enterprise | G20: Cohort 1: Upgrades in progress | H20: 1247274 | M20: =IF($B20="","",COUNTIFS('Blocker log'!$A:$A,$B20,'Blocker log'!$G:$G,"<>")) -> 0 | N20: =IF($B20="","",COUNTIFS('Blocker log'!$A:$A,$B20,'Blocker log'!$G:$G,"Hard blocker")) -> 0 | O20: =IF($B20="","",COUNTIFS('Blocker log'!$A:$A,$B20,'Blocker log'!$G:$G,"Hard blocker",'Blocker log'!$L:$L,9)) -> 0 | P20: =IF($B20="","",MAXIFS('Blocker log'!$L:$L,'Blocker log'!$A:$A,$B20,'Blocker log'!$G:$G,"Hard blocker")) -> 0 | Q20: =IF($B20="","",IF($K20<>"Complete","Assessment pending",IF($N20=0,"Ready now",VLOOKUP($P20,Lists!$D$2:$E$5,2,FALSE)))) -> Assessment pending
A21: 0017000000mir1qAAA | B21: Texas Children's Hospital | C21: Tier 2 | D21: AMER | E21: AMER Strategic West | F21: AMER Strategic West Healthcare West | G21: Cohort 1: Upgrades in progress | H21: 190663 | I21: Farooq Abrahem | K21: Pending | M21: =IF($B21="","",COUNTIFS('Blocker log'!$A:$A,$B21,'Blocker log'!$G:$G,"<>")) -> 0 | N21: =IF($B21="","",COUNTIFS('Blocker log'!$A:$A,$B21,'Blocker log'!$G:$G,"Hard blocker")) -> 0 | O21: =IF($B21="","",COUNTIFS('Blocker log'!$A:$A,$B21,'Blocker log'!$G:$G,"Hard blocker",'Blocker log'!$L:$L,9)) -> 0 | P21: =IF($B21="","",MAXIFS('Blocker log'!$L:$L,'Blocker log'!$A:$A,$B21,'Blocker log'!$G:$G,"Hard blocker")) -> 0 | Q21: =IF($B21="","",IF($K21<>"Complete","Assessment pending",IF($N21=0,"Ready now",VLOOKUP($P21,Lists!$D$2:$E$5,2,FALSE)))) -> Assessment pending
A22: 0017000000dx6OMAAY | B22: The PNC Financial Services Group, Inc. | C22: Tier 2 | D22: AMER | E22: AMER Strategic Central | F22: AMER Strategic Central Ohio Valley | G22: Cohort 1: Upgrades in progress | H22: 137721 | I22: Farooq Abrahem | K22: Pending | M22: =IF($B22="","",COUNTIFS('Blocker log'!$A:$A,$B22,'Blocker log'!$G:$G,"<>")) -> 0 | N22: =IF($B22="","",COUNTIFS('Blocker log'!$A:$A,$B22,'Blocker log'!$G:$G,"Hard blocker")) -> 0 | O22: =IF($B22="","",COUNTIFS('Blocker log'!$A:$A,$B22,'Blocker log'!$G:$G,"Hard blocker",'Blocker log'!$L:$L,9)) -> 0 | P22: =IF($B22="","",MAXIFS('Blocker log'!$L:$L,'Blocker log'!$A:$A,$B22,'Blocker log'!$G:$G,"Hard blocker")) -> 0 | Q22: =IF($B22="","",IF($K22<>"Complete","Assessment pending",IF($N22=0,"Ready now",VLOOKUP($P22,Lists!$D$2:$E$5,2,FALSE)))) -> Assessment pending
A23: 0017000000MfHihAAF | B23: Franciscan Alliance, Inc. | C23: Tier 2 | D23: AMER | E23: AMER Strategic West | F23: AMER Strategic West Healthcare East | G23: Cohort 1: Upgrades in progress | H23: 161409 | I23: Farooq Abrahem | K23: Pending | M23: =IF($B23="","",COUNTIFS('Blocker log'!$A:$A,$B23,'Blocker log'!$G:$G,"<>")) -> 0 | N23: =IF($B23="","",COUNTIFS('Blocker log'!$A:$A,$B23,'Blocker log'!$G:$G,"Hard blocker")) -> 0 | O23: =IF($B23="","",COUNTIFS('Blocker log'!$A:$A,$B23,'Blocker log'!$G:$G,"Hard blocker",'Blocker log'!$L:$L,9)) -> 0 | P23: =IF($B23="","",MAXIFS('Blocker log'!$L:$L,'Blocker log'!$A:$A,$B23,'Blocker log'!$G:$G,"Hard blocker")) -> 0 | Q23: =IF($B23="","",IF($K23<>"Complete","Assessment pending",IF($N23=0,"Ready now",VLOOKUP($P23,Lists!$D$2:$E$5,2,FALSE)))) -> Assessment pending
A24: 001700000137WgRAAU | B24: Wind River Systems, Inc. | C24: Tier 2 | D24: AMER | E24: AMER Strategic Central | F24: AMER Strategic Central Texas | G24: Cohort 1: Upgrades in progress | H24: 148120 | I24: Farooq Abrahem | K24: Pending | M24: =IF($B24="","",COUNTIFS('Blocker log'!$A:$A,$B24,'Blocker log'!$G:$G,"<>")) -> 0 | N24: =IF($B24="","",COUNTIFS('Blocker log'!$A:$A,$B24,'Blocker log'!$G:$G,"Hard blocker")) -> 0 | O24: =IF($B24="","",COUNTIFS('Blocker log'!$A:$A,$B24,'Blocker log'!$G:$G,"Hard blocker",'Blocker log'!$L:$L,9)) -> 0 | P24: =IF($B24="","",MAXIFS('Blocker log'!$L:$L,'Blocker log'!$A:$A,$B24,'Blocker log'!$G:$G,"Hard blocker")) -> 0 | Q24: =IF($B24="","",IF($K24<>"Complete","Assessment pending",IF($N24=0,"Ready now",VLOOKUP($P24,Lists!$D$2:$E$5,2,FALSE)))) -> Assessment pending
A25: 0017000000kbOIVAA2 | B25: Lg Uplus Corp. | C25: Tier 1 | D25: JAPAC | E25: Korea | F25: Korea | G25: Cohort 1: Upgrades in progress | H25: 755874 | I25: Jane Shin | K25: Pending | M25: =IF($B25="","",COUNTIFS('Blocker log'!$A:$A,$B25,'Blocker log'!$G:$G,"<>")) -> 0 | N25: =IF($B25="","",COUNTIFS('Blocker log'!$A:$A,$B25,'Blocker log'!$G:$G,"Hard blocker")) -> 0 | O25: =IF($B25="","",COUNTIFS('Blocker log'!$A:$A,$B25,'Blocker log'!$G:$G,"Hard blocker",'Blocker log'!$L:$L,9)) -> 0 | P25: =IF($B25="","",MAXIFS('Blocker log'!$L:$L,'Blocker log'!$A:$A,$B25,'Blocker log'!$G:$G,"Hard blocker")) -> 0 | Q25: =IF($B25="","",IF($K25<>"Complete","Assessment pending",IF($N25=0,"Ready now",VLOOKUP($P25,Lists!$D$2:$E$5,2,FALSE)))) -> Assessment pending
A26: 0017000000dN3dfAAC | B26: Salesforce.Com, Inc. | C26: Tier 1 | D26: AMER | E26: AMER Strategic West | F26: AMER Strategic West NorCal | G26: Cohort 1: Upgrades in progress | H26: 13604812 | I26: Khizar Karim | K26: Pending | M26: =IF($B26="","",COUNTIFS('Blocker log'!$A:$A,$B26,'Blocker log'!$G:$G,"<>")) -> 0 | N26: =IF($B26="","",COUNTIFS('Blocker log'!$A:$A,$B26,'Blocker log'!$G:$G,"Hard blocker")) -> 0 | O26: =IF($B26="","",COUNTIFS('Blocker log'!$A:$A,$B26,'Blocker log'!$G:$G,"Hard blocker",'Blocker log'!$L:$L,9)) -> 0 | P26: =IF($B26="","",MAXIFS('Blocker log'!$L:$L,'Blocker log'!$A:$A,$B26,'Blocker log'!$G:$G,"Hard blocker")) -> 0 | Q26: =IF($B26="","",IF($K26<>"Complete","Assessment pending",IF($N26=0,"Ready now",VLOOKUP($P26,Lists!$D$2:$E$5,2,FALSE)))) -> Assessment pending
A27: 0017000000qx0YBAAY | B27: Marriott International, Inc. | C27: Tier 1 | D27: AMER | E27: AMER Strategic East | F27: AMER Strategic East MidAtlantic | G27: Cohort 1: Upgrades in progress | H27: 1159779 | I27: Khizar Karim | K27: Pending | M27: =IF($B27="","",COUNTIFS('Blocker log'!$A:$A,$B27,'Blocker log'!$G:$G,"<>")) -> 0 | N27: =IF($B27="","",COUNTIFS('Blocker log'!$A:$A,$B27,'Blocker log'!$G:$G,"Hard blocker")) -> 0 | O27: =IF($B27="","",COUNTIFS('Blocker log'!$A:$A,$B27,'Blocker log'!$G:$G,"Hard blocker",'Blocker log'!$L:$L,9)) -> 0 | P27: =IF($B27="","",MAXIFS('Blocker log'!$L:$L,'Blocker log'!$A:$A,$B27,'Blocker log'!$G:$G,"Hard blocker")) -> 0 | Q27: =IF($B27="","",IF($K27<>"Complete","Assessment pending",IF($N27=0,"Ready now",VLOOKUP($P27,Lists!$D$2:$E$5,2,FALSE)))) -> Assessment pending
A28: 0014u00001tEzw8AAC | B28: Dh Business Services Llc | C28: Tier 1 | D28: AMER | E28: AMER Strategic East | F28: AMER Strategic East Northeast | G28: Cohort 1: Upgrades in progress | H28: 773 | I28: Khizar Karim | K28: Pending | M28: =IF($B28="","",COUNTIFS('Blocker log'!$A:$A,$B28,'Blocker log'!$G:$G,"<>")) -> 0 | N28: =IF($B28="","",COUNTIFS('Blocker log'!$A:$A,$B28,'Blocker log'!$G:$G,"Hard blocker")) -> 0 | O28: =IF($B28="","",COUNTIFS('Blocker log'!$A:$A,$B28,'Blocker log'!$G:$G,"Hard blocker",'Blocker log'!$L:$L,9)) -> 0 | P28: =IF($B28="","",MAXIFS('Blocker log'!$L:$L,'Blocker log'!$A:$A,$B28,'Blocker log'!$G:$G,"Hard blocker")) -> 0 | Q28: =IF($B28="","",IF($K28<>"Complete","Assessment pending",IF($N28=0,"Ready now",VLOOKUP($P28,Lists!$D$2:$E$5,2,FALSE)))) -> Assessment pending
A29: 0017000000peq8uAAA | B29: Tory Burch LLC | C29: Tier 2 | D29: AMER | E29: AMER Strategic East | F29: AMER Strategic East NY Enterprise | G29: Cohort 1: Upgrades in progress | H29: 191798 | I29: Khizar Karim | K29: Pending | M29: =IF($B29="","",COUNTIFS('Blocker log'!$A:$A,$B29,'Blocker log'!$G:$G,"<>")) -> 0 | N29: =IF($B29="","",COUNTIFS('Blocker log'!$A:$A,$B29,'Blocker log'!$G:$G,"Hard blocker")) -> 0 | O29: =IF($B29="","",COUNTIFS('Blocker log'!$A:$A,$B29,'Blocker log'!$G:$G,"Hard blocker",'Blocker log'!$L:$L,9)) -> 0 | P29: =IF($B29="","",MAXIFS('Blocker log'!$L:$L,'Blocker log'!$A:$A,$B29,'Blocker log'!$G:$G,"Hard blocker")) -> 0 | Q29: =IF($B29="","",IF($K29<>"Complete","Assessment pending",IF($N29=0,"Ready now",VLOOKUP($P29,Lists!$D$2:$E$5,2,FALSE)))) -> Assessment pending
A30: 0017000000nBDuXAAW | B30: Factory Mutual Insurance Co | C30: Tier 2 | D30: AMER | E30: AMER Strategic East | F30: AMER Strategic East Northeast | G30: Cohort 1: Upgrades in progress | I30: Khizar Karim | K30: Pending | M30: =IF($B30="","",COUNTIFS('Blocker log'!$A:$A,$B30,'Blocker log'!$G:$G,"<>")) -> 0 | N30: =IF($B30="","",COUNTIFS('Blocker log'!$A:$A,$B30,'Blocker log'!$G:$G,"Hard blocker")) -> 0 | O30: =IF($B30="","",COUNTIFS('Blocker log'!$A:$A,$B30,'Blocker log'!$G:$G,"Hard blocker",'Blocker log'!$L:$L,9)) -> 0 | P30: =IF($B30="","",MAXIFS('Blocker log'!$L:$L,'Blocker log'!$A:$A,$B30,'Blocker log'!$G:$G,"Hard blocker")) -> 0 | Q30: =IF($B30="","",IF($K30<>"Complete","Assessment pending",IF($N30=0,"Ready now",VLOOKUP($P30,Lists!$D$2:$E$5,2,FALSE)))) -> Assessment pending
A31: 0017000000cJCU8AAO | B31: Cox Communications, Inc. | C31: Tier 1 | D31: AMER | E31: AMER Strategic East | F31: AMER Strategic East SI/SP | G31: Cohort 1: Upgrades in progress | H31: 55880 | I31: Lauren Megrelis | K31: Pending | M31: =IF($B31="","",COUNTIFS('Blocker log'!$A:$A,$B31,'Blocker log'!$G:$G,"<>")) -> 0 | N31: =IF($B31="","",COUNTIFS('Blocker log'!$A:$A,$B31,'Blocker log'!$G:$G,"Hard blocker")) -> 0 | O31: =IF($B31="","",COUNTIFS('Blocker log'!$A:$A,$B31,'Blocker log'!$G:$G,"Hard blocker",'Blocker log'!$L:$L,9)) -> 0 | P31: =IF($B31="","",MAXIFS('Blocker log'!$L:$L,'Blocker log'!$A:$A,$B31,'Blocker log'!$G:$G,"Hard blocker")) -> 0 | Q31: =IF($B31="","",IF($K31<>"Complete","Assessment pending",IF($N31=0,"Ready now",VLOOKUP($P31,Lists!$D$2:$E$5,2,FALSE)))) -> Assessment pending
A32: 0017000000jEETMAA4 | B32: Medidata Solutions Worldwide | C32: Tier 1 | D32: AMER | E32: AMER Strategic East | F32: AMER Strategic East NY Enterprise | G32: Cohort 1: Upgrades in progress | H32: 807516 | I32: Lauren Megrelis | K32: Pending | M32: =IF($B32="","",COUNTIFS('Blocker log'!$A:$A,$B32,'Blocker log'!$G:$G,"<>")) -> 0 | N32: =IF($B32="","",COUNTIFS('Blocker log'!$A:$A,$B32,'Blocker log'!$G:$G,"Hard blocker")) -> 0 | O32: =IF($B32="","",COUNTIFS('Blocker log'!$A:$A,$B32,'Blocker log'!$G:$G,"Hard blocker",'Blocker log'!$L:$L,9)) -> 0 | P32: =IF($B32="","",MAXIFS('Blocker log'!$L:$L,'Blocker log'!$A:$A,$B32,'Blocker log'!$G:$G,"Hard blocker")) -> 0 | Q32: =IF($B32="","",IF($K32<>"Complete","Assessment pending",IF($N32=0,"Ready now",VLOOKUP($P32,Lists!$D$2:$E$5,2,FALSE)))) -> Assessment pending
A33: 0017000001V49vrAAB | B33: Everbridge, Inc. | C33: Tier 2 | D33: AMER | E33: AMER Commercial | F33: Select East | G33: Cohort 1: Upgrades in progress | H33: 63515 | I33: Lauren Megrelis | K33: Pending | M33: =IF($B33="","",COUNTIFS('Blocker log'!$A:$A,$B33,'Blocker log'!$G:$G,"<>")) -> 0 | N33: =IF($B33="","",COUNTIFS('Blocker log'!$A:$A,$B33,'Blocker log'!$G:$G,"Hard blocker")) -> 0 | O33: =IF($B33="","",COUNTIFS('Blocker log'!$A:$A,$B33,'Blocker log'!$G:$G,"Hard blocker",'Blocker log'!$L:$L,9)) -> 0 | P33: =IF($B33="","",MAXIFS('Blocker log'!$L:$L,'Blocker log'!$A:$A,$B33,'Blocker log'!$G:$G,"Hard blocker")) -> 0 | Q33: =IF($B33="","",IF($K33<>"Complete","Assessment pending",IF($N33=0,"Ready now",VLOOKUP($P33,Lists!$D$2:$E$5,2,FALSE)))) -> Assessment pending
A34: 0017000000t9fPSAAY | B34: Memorial Sloan-Kettering Cancer Center | C34: Tier 2 | D34: AMER | E34: AMER Strategic West | F34: AMER Strategic West Healthcare East | G34: Cohort 1: Upgrades in progress | H34: 223497 | I34: Lauren Megrelis | K34: Pending | M34: =IF($B34="","",COUNTIFS('Blocker log'!$A:$A,$B34,'Blocker log'!$G:$G,"<>")) -> 0 | N34: =IF($B34="","",COUNTIFS('Blocker log'!$A:$A,$B34,'Blocker log'!$G:$G,"Hard blocker")) -> 0 | O34: =IF($B34="","",COUNTIFS('Blocker log'!$A:$A,$B34,'Blocker log'!$G:$G,"Hard blocker",'Blocker log'!$L:$L,9)) -> 0 | P34: =IF($B34="","",MAXIFS('Blocker log'!$L:$L,'Blocker log'!$A:$A,$B34,'Blocker log'!$G:$G,"Hard blocker")) -> 0 | Q34: =IF($B34="","",IF($K34<>"Complete","Assessment pending",IF($N34=0,"Ready now",VLOOKUP($P34,Lists!$D$2:$E$5,2,FALSE)))) -> Assessment pending
A35: 0014u0000238d8uAAA | B35: Corebridge Financial, Inc. | C35: Tier 1 | D35: AMER | E35: AMER Strategic East | F35: AMER Strategic East FIS | G35: Cohort 1: Upgrades in progress | H35: 36000 | M35: =IF($B35="","",COUNTIFS('Blocker log'!$A:$A,$B35,'Blocker log'!$G:$G,"<>")) -> 0 | N35: =IF($B35="","",COUNTIFS('Blocker log'!$A:$A,$B35,'Blocker log'!$G:$G,"Hard blocker")) -> 0 | O35: =IF($B35="","",COUNTIFS('Blocker log'!$A:$A,$B35,'Blocker log'!$G:$G,"Hard blocker",'Blocker log'!$L:$L,9)) -> 0 | P35: =IF($B35="","",MAXIFS('Blocker log'!$L:$L,'Blocker log'!$A:$A,$B35,'Blocker log'!$G:$G,"Hard blocker")) -> 0 | Q35: =IF($B35="","",IF($K35<>"Complete","Assessment pending",IF($N35=0,"Ready now",VLOOKUP($P35,Lists!$D$2:$E$5,2,FALSE)))) -> Assessment pending
A36: 0014u000029psomAAA | B36: Optus Systems Pty Ltd | C36: Tier 1 | D36: JAPAC | E36: ANZ | F36: ANZ East Coast Majors | G36: Cohort 1: Upgrades in progress | H36: 325882 | M36: =IF($B36="","",COUNTIFS('Blocker log'!$A:$A,$B36,'Blocker log'!$G:$G,"<>")) -> 0 | N36: =IF($B36="","",COUNTIFS('Blocker log'!$A:$A,$B36,'Blocker log'!$G:$G,"Hard blocker")) -> 0 | O36: =IF($B36="","",COUNTIFS('Blocker log'!$A:$A,$B36,'Blocker log'!$G:$G,"Hard blocker",'Blocker log'!$L:$L,9)) -> 0 | P36: =IF($B36="","",MAXIFS('Blocker log'!$L:$L,'Blocker log'!$A:$A,$B36,'Blocker log'!$G:$G,"Hard blocker")) -> 0 | Q36: =IF($B36="","",IF($K36<>"Complete","Assessment pending",IF($N36=0,"Ready now",VLOOKUP($P36,Lists!$D$2:$E$5,2,FALSE)))) -> Assessment pending
A37: 0017000000bFh2TAAS | B37: The Chubb Corporation | C37: Tier 1 | D37: AMER | E37: AMER Strategic East | F37: AMER Strategic East FIS | G37: Cohort 1: Upgrades in progress | H37: 735868 | M37: =IF($B37="","",COUNTIFS('Blocker log'!$A:$A,$B37,'Blocker log'!$G:$G,"<>")) -> 0 | N37: =IF($B37="","",COUNTIFS('Blocker log'!$A:$A,$B37,'Blocker log'!$G:$G,"Hard blocker")) -> 0 | O37: =IF($B37="","",COUNTIFS('Blocker log'!$A:$A,$B37,'Blocker log'!$G:$G,"Hard blocker",'Blocker log'!$L:$L,9)) -> 0 | P37: =IF($B37="","",MAXIFS('Blocker log'!$L:$L,'Blocker log'!$A:$A,$B37,'Blocker log'!$G:$G,"Hard blocker")) -> 0 | Q37: =IF($B37="","",IF($K37<>"Complete","Assessment pending",IF($N37=0,"Ready now",VLOOKUP($P37,Lists!$D$2:$E$5,2,FALSE)))) -> Assessment pending
A38: 0014u00001x8rNFAAY | B38: Movable Ink | C38: Tier 2 | D38: AMER | E38: AMER Commercial | F38: Select East | G38: Cohort 1: Upgrades in progress | H38: 155635 | I38: Lauren Megrelis | K38: Pending | M38: =IF($B38="","",COUNTIFS('Blocker log'!$A:$A,$B38,'Blocker log'!$G:$G,"<>")) -> 0 | N38: =IF($B38="","",COUNTIFS('Blocker log'!$A:$A,$B38,'Blocker log'!$G:$G,"Hard blocker")) -> 0 | O38: =IF($B38="","",COUNTIFS('Blocker log'!$A:$A,$B38,'Blocker log'!$G:$G,"Hard blocker",'Blocker log'!$L:$L,9)) -> 0 | P38: =IF($B38="","",MAXIFS('Blocker log'!$L:$L,'Blocker log'!$A:$A,$B38,'Blocker log'!$G:$G,"Hard blocker")) -> 0 | Q38: =IF($B38="","",IF($K38<>"Complete","Assessment pending",IF($N38=0,"Ready now",VLOOKUP($P38,Lists!$D$2:$E$5,2,FALSE)))) -> Assessment pending
A39: 0017000000RGL6UAAX | B39: American Express Company | C39: Tier 1 | D39: AMER | E39: AMER Strategic West | F39: AMER Strategic West MTN | G39: Cohort 1: Upgrades in progress | H39: 1872802 | I39: Lindsey Smith | K39: Pending | M39: =IF($B39="","",COUNTIFS('Blocker log'!$A:$A,$B39,'Blocker log'!$G:$G,"<>")) -> 0 | N39: =IF($B39="","",COUNTIFS('Blocker log'!$A:$A,$B39,'Blocker log'!$G:$G,"Hard blocker")) -> 0 | O39: =IF($B39="","",COUNTIFS('Blocker log'!$A:$A,$B39,'Blocker log'!$G:$G,"Hard blocker",'Blocker log'!$L:$L,9)) -> 0 | P39: =IF($B39="","",MAXIFS('Blocker log'!$L:$L,'Blocker log'!$A:$A,$B39,'Blocker log'!$G:$G,"Hard blocker")) -> 0 | Q39: =IF($B39="","",IF($K39<>"Complete","Assessment pending",IF($N39=0,"Ready now",VLOOKUP($P39,Lists!$D$2:$E$5,2,FALSE)))) -> Assessment pending
A40: 0017000000peemgAAA | B40: Micron Technologies, Inc | C40: Tier 2 | D40: AMER | E40: AMER Strategic West | F40: AMER Strategic West PNW | G40: Cohort 1: Upgrades in progress | H40: 667543 | I40: Lindsey Smith | K40: Pending | M40: =IF($B40="","",COUNTIFS('Blocker log'!$A:$A,$B40,'Blocker log'!$G:$G,"<>")) -> 0 | N40: =IF($B40="","",COUNTIFS('Blocker log'!$A:$A,$B40,'Blocker log'!$G:$G,"Hard blocker")) -> 0 | O40: =IF($B40="","",COUNTIFS('Blocker log'!$A:$A,$B40,'Blocker log'!$G:$G,"Hard blocker",'Blocker log'!$L:$L,9)) -> 0 | P40: =IF($B40="","",MAXIFS('Blocker log'!$L:$L,'Blocker log'!$A:$A,$B40,'Blocker log'!$G:$G,"Hard blocker")) -> 0 | Q40: =IF($B40="","",IF($K40<>"Complete","Assessment pending",IF($N40=0,"Ready now",VLOOKUP($P40,Lists!$D$2:$E$5,2,FALSE)))) -> Assessment pending
A41: 0017000000ZN93ZAAT | B41: Kaiser Permanente | C41: Tier 1 | D41: AMER | E41: AMER Strategic West | F41: AMER Strategic West Healthcare West | G41: Cohort 1: Upgrades in progress | H41: 93655 | I41: Muhammad Ali | K41: Complete | L41: 46316 | M41: =IF($B41="","",COUNTIFS('Blocker log'!$A:$A,$B41,'Blocker log'!$G:$G,"<>")) -> 3 | N41: =IF($B41="","",COUNTIFS('Blocker log'!$A:$A,$B41,'Blocker log'!$G:$G,"Hard blocker")) -> 1 | O41: =IF($B41="","",COUNTIFS('Blocker log'!$A:$A,$B41,'Blocker log'!$G:$G,"Hard blocker",'Blocker log'!$L:$L,9)) -> 0 | P41: =IF($B41="","",MAXIFS('Blocker log'!$L:$L,'Blocker log'!$A:$A,$B41,'Blocker log'!$G:$G,"Hard blocker")) -> 0 | Q41: =IF($B41="","",IF($K41<>"Complete","Assessment pending",IF($N41=0,"Ready now",VLOOKUP($P41,Lists!$D$2:$E$5,2,FALSE)))) -> #N/A
A42: 0010g00001hXpCsAAK | B42: Applied Materials | C42: Tier 2 | D42: AMER | E42: AMER Strategic West | F42: AMER Strategic West NorCal | G42: Cohort 1: Upgrades in progress | H42: 245751 | I42: Muhammad Ali | M42: =IF($B42="","",COUNTIFS('Blocker log'!$A:$A,$B42,'Blocker log'!$G:$G,"<>")) -> 0 | N42: =IF($B42="","",COUNTIFS('Blocker log'!$A:$A,$B42,'Blocker log'!$G:$G,"Hard blocker")) -> 0 | O42: =IF($B42="","",COUNTIFS('Blocker log'!$A:$A,$B42,'Blocker log'!$G:$G,"Hard blocker",'Blocker log'!$L:$L,9)) -> 0 | P42: =IF($B42="","",MAXIFS('Blocker log'!$L:$L,'Blocker log'!$A:$A,$B42,'Blocker log'!$G:$G,"Hard blocker")) -> 0 | Q42: =IF($B42="","",IF($K42<>"Complete","Assessment pending",IF($N42=0,"Ready now",VLOOKUP($P42,Lists!$D$2:$E$5,2,FALSE)))) -> Assessment pending
A43: 0017000000scHxAAAU | B43: Meijer, Inc. | C43: Tier 2 | D43: AMER | E43: AMER Strategic Central | F43: AMER Strategic Central Ohio Valley | G43: Cohort 1: Upgrades in progress | H43: 421200 | I43: Muhammad Ali | K43: Complete | L43: 46321 | M43: =IF($B43="","",COUNTIFS('Blocker log'!$A:$A,$B43,'Blocker log'!$G:$G,"<>")) -> 0 | N43: =IF($B43="","",COUNTIFS('Blocker log'!$A:$A,$B43,'Blocker log'!$G:$G,"Hard blocker")) -> 0 | O43: =IF($B43="","",COUNTIFS('Blocker log'!$A:$A,$B43,'Blocker log'!$G:$G,"Hard blocker",'Blocker log'!$L:$L,9)) -> 0 | P43: =IF($B43="","",MAXIFS('Blocker log'!$L:$L,'Blocker log'!$A:$A,$B43,'Blocker log'!$G:$G,"Hard blocker")) -> 0 | Q43: =IF($B43="","",IF($K43<>"Complete","Assessment pending",IF($N43=0,"Ready now",VLOOKUP($P43,Lists!$D$2:$E$5,2,FALSE)))) -> Ready now
A44: 0017000000kYwckAAC | B44: L'Oreal | C44: Tier 2 | D44: EMEA | E44: France | F44: France Strategic | G44: Cohort 1: Upgrades in progress | H44: 556043 | M44: =IF($B44="","",COUNTIFS('Blocker log'!$A:$A,$B44,'Blocker log'!$G:$G,"<>")) -> 0 | N44: =IF($B44="","",COUNTIFS('Blocker log'!$A:$A,$B44,'Blocker log'!$G:$G,"Hard blocker")) -> 0 | O44: =IF($B44="","",COUNTIFS('Blocker log'!$A:$A,$B44,'Blocker log'!$G:$G,"Hard blocker",'Blocker log'!$L:$L,9)) -> 0 | P44: =IF($B44="","",MAXIFS('Blocker log'!$L:$L,'Blocker log'!$A:$A,$B44,'Blocker log'!$G:$G,"Hard blocker")) -> 0 | Q44: =IF($B44="","",IF($K44<>"Complete","Assessment pending",IF($N44=0,"Ready now",VLOOKUP($P44,Lists!$D$2:$E$5,2,FALSE)))) -> Assessment pending
A45: 0017000000os81PAAQ | B45: Worley Parsons Limited | C45: Tier 2 | D45: AMER | E45: AMER Strategic Central | F45: AMER Strategic Central Texas | G45: Cohort 1: Upgrades in progress | H45: 448318 | M45: =IF($B45="","",COUNTIFS('Blocker log'!$A:$A,$B45,'Blocker log'!$G:$G,"<>")) -> 0 | N45: =IF($B45="","",COUNTIFS('Blocker log'!$A:$A,$B45,'Blocker log'!$G:$G,"Hard blocker")) -> 0 | O45: =IF($B45="","",COUNTIFS('Blocker log'!$A:$A,$B45,'Blocker log'!$G:$G,"Hard blocker",'Blocker log'!$L:$L,9)) -> 0 | P45: =IF($B45="","",MAXIFS('Blocker log'!$L:$L,'Blocker log'!$A:$A,$B45,'Blocker log'!$G:$G,"Hard blocker")) -> 0 | Q45: =IF($B45="","",IF($K45<>"Complete","Assessment pending",IF($N45=0,"Ready now",VLOOKUP($P45,Lists!$D$2:$E$5,2,FALSE)))) -> Assessment pending
A46: 0017000000gGsAhAAK | B46: Cantor Fitzgerald Technology Markets, LLC | C46: Tier 2 | D46: AMER | E46: AMER Strategic East | F46: AMER Strategic East NY Enterprise | G46: Cohort 1: Upgrades in progress | H46: 312371 | M46: =IF($B46="","",COUNTIFS('Blocker log'!$A:$A,$B46,'Blocker log'!$G:$G,"<>")) -> 0 | N46: =IF($B46="","",COUNTIFS('Blocker log'!$A:$A,$B46,'Blocker log'!$G:$G,"Hard blocker")) -> 0 | O46: =IF($B46="","",COUNTIFS('Blocker log'!$A:$A,$B46,'Blocker log'!$G:$G,"Hard blocker",'Blocker log'!$L:$L,9)) -> 0 | P46: =IF($B46="","",MAXIFS('Blocker log'!$L:$L,'Blocker log'!$A:$A,$B46,'Blocker log'!$G:$G,"Hard blocker")) -> 0 | Q46: =IF($B46="","",IF($K46<>"Complete","Assessment pending",IF($N46=0,"Ready now",VLOOKUP($P46,Lists!$D$2:$E$5,2,FALSE)))) -> Assessment pending
A47: 0017000000q3Y2KAAU | B47: Blue Cross Blue Shield Association (HQ) | C47: Tier 2 | D47: AMER | E47: AMER Strategic Central | F47: AMER Strategic Central Northcentral | G47: Cohort 1: Upgrades in progress | H47: 536097 | M47: =IF($B47="","",COUNTIFS('Blocker log'!$A:$A,$B47,'Blocker log'!$G:$G,"<>")) -> 0 | N47: =IF($B47="","",COUNTIFS('Blocker log'!$A:$A,$B47,'Blocker log'!$G:$G,"Hard blocker")) -> 0 | O47: =IF($B47="","",COUNTIFS('Blocker log'!$A:$A,$B47,'Blocker log'!$G:$G,"Hard blocker",'Blocker log'!$L:$L,9)) -> 0 | P47: =IF($B47="","",MAXIFS('Blocker log'!$L:$L,'Blocker log'!$A:$A,$B47,'Blocker log'!$G:$G,"Hard blocker")) -> 0 | Q47: =IF($B47="","",IF($K47<>"Complete","Assessment pending",IF($N47=0,"Ready now",VLOOKUP($P47,Lists!$D$2:$E$5,2,FALSE)))) -> Assessment pending
A48: 0017000000cIg6KAAS | B48: Vanderbilt Health | C48: Tier 2 | D48: AMER | E48: AMER Strategic West | F48: AMER Strategic West Healthcare East | G48: Cohort 1: Upgrades in progress | H48: 414399 | M48: =IF($B48="","",COUNTIFS('Blocker log'!$A:$A,$B48,'Blocker log'!$G:$G,"<>")) -> 0 | N48: =IF($B48="","",COUNTIFS('Blocker log'!$A:$A,$B48,'Blocker log'!$G:$G,"Hard blocker")) -> 0 | O48: =IF($B48="","",COUNTIFS('Blocker log'!$A:$A,$B48,'Blocker log'!$G:$G,"Hard blocker",'Blocker log'!$L:$L,9)) -> 0 | P48: =IF($B48="","",MAXIFS('Blocker log'!$L:$L,'Blocker log'!$A:$A,$B48,'Blocker log'!$G:$G,"Hard blocker")) -> 0 | Q48: =IF($B48="","",IF($K48<>"Complete","Assessment pending",IF($N48=0,"Ready now",VLOOKUP($P48,Lists!$D$2:$E$5,2,FALSE)))) -> Assessment pending
A49: 0017000001XPl7OAAT | B49: Tarjeta Naranja S.a. | C49: Tier 2 | D49: LATAM | E49: MCA South | F49: MCA South | G49: Cohort 1: Upgrades in progress | H49: 521948 | M49: =IF($B49="","",COUNTIFS('Blocker log'!$A:$A,$B49,'Blocker log'!$G:$G,"<>")) -> 0 | N49: =IF($B49="","",COUNTIFS('Blocker log'!$A:$A,$B49,'Blocker log'!$G:$G,"Hard blocker")) -> 0 | O49: =IF($B49="","",COUNTIFS('Blocker log'!$A:$A,$B49,'Blocker log'!$G:$G,"Hard blocker",'Blocker log'!$L:$L,9)) -> 0 | P49: =IF($B49="","",MAXIFS('Blocker log'!$L:$L,'Blocker log'!$A:$A,$B49,'Blocker log'!$G:$G,"Hard blocker")) -> 0 | Q49: =IF($B49="","",IF($K49<>"Complete","Assessment pending",IF($N49=0,"Ready now",VLOOKUP($P49,Lists!$D$2:$E$5,2,FALSE)))) -> Assessment pending
A50: 0017000000nyW1fAAE | B50: Air Liquide S.A. | C50: Tier 2 | D50: EMEA | E50: France | F50: France Strategic | G50: Cohort 1: Upgrades in progress | H50: 221649 | M50: =IF($B50="","",COUNTIFS('Blocker log'!$A:$A,$B50,'Blocker log'!$G:$G,"<>")) -> 0 | N50: =IF($B50="","",COUNTIFS('Blocker log'!$A:$A,$B50,'Blocker log'!$G:$G,"Hard blocker")) -> 0 | O50: =IF($B50="","",COUNTIFS('Blocker log'!$A:$A,$B50,'Blocker log'!$G:$G,"Hard blocker",'Blocker log'!$L:$L,9)) -> 0 | P50: =IF($B50="","",MAXIFS('Blocker log'!$L:$L,'Blocker log'!$A:$A,$B50,'Blocker log'!$G:$G,"Hard blocker")) -> 0 | Q50: =IF($B50="","",IF($K50<>"Complete","Assessment pending",IF($N50=0,"Ready now",VLOOKUP($P50,Lists!$D$2:$E$5,2,FALSE)))) -> Assessment pending
A51: 0017000000tfianAAA | B51: Diagnosticos da America S/A. | C51: Tier 2 | D51: LATAM | E51: Brazil | F51: Brazil | G51: Cohort 1: Upgrades in progress | H51: 216512 | M51: =IF($B51="","",COUNTIFS('Blocker log'!$A:$A,$B51,'Blocker log'!$G:$G,"<>")) -> 0 | N51: =IF($B51="","",COUNTIFS('Blocker log'!$A:$A,$B51,'Blocker log'!$G:$G,"Hard blocker")) -> 0 | O51: =IF($B51="","",COUNTIFS('Blocker log'!$A:$A,$B51,'Blocker log'!$G:$G,"Hard blocker",'Blocker log'!$L:$L,9)) -> 0 | P51: =IF($B51="","",MAXIFS('Blocker log'!$L:$L,'Blocker log'!$A:$A,$B51,'Blocker log'!$G:$G,"Hard blocker")) -> 0 | Q51: =IF($B51="","",IF($K51<>"Complete","Assessment pending",IF($N51=0,"Ready now",VLOOKUP($P51,Lists!$D$2:$E$5,2,FALSE)))) -> Assessment pending
A52: 0017000000tAmAHAA0 | B52: Score Media and Gaming Inc. | C52: Tier 2 | D52: AMER | E52: AMER Canada | F52: Canada Central | G52: Cohort 1: Upgrades in progress | H52: 509056 | M52: =IF($B52="","",COUNTIFS('Blocker log'!$A:$A,$B52,'Blocker log'!$G:$G,"<>")) -> 0 | N52: =IF($B52="","",COUNTIFS('Blocker log'!$A:$A,$B52,'Blocker log'!$G:$G,"Hard blocker")) -> 0 | O52: =IF($B52="","",COUNTIFS('Blocker log'!$A:$A,$B52,'Blocker log'!$G:$G,"Hard blocker",'Blocker log'!$L:$L,9)) -> 0 | P52: =IF($B52="","",MAXIFS('Blocker log'!$L:$L,'Blocker log'!$A:$A,$B52,'Blocker log'!$G:$G,"Hard blocker")) -> 0 | Q52: =IF($B52="","",IF($K52<>"Complete","Assessment pending",IF($N52=0,"Ready now",VLOOKUP($P52,Lists!$D$2:$E$5,2,FALSE)))) -> Assessment pending
A53: 0017000000ZLRJNAA5 | B53: Aaron's, Inc. | C53: Tier 2 | D53: AMER | E53: AMER Strategic Central | F53: AMER Strategic Central Ohio Valley | G53: Cohort 1: Upgrades in progress | H53: 113106 | I53: Muhammad Ali | M53: =IF($B53="","",COUNTIFS('Blocker log'!$A:$A,$B53,'Blocker log'!$G:$G,"<>")) -> 0 | N53: =IF($B53="","",COUNTIFS('Blocker log'!$A:$A,$B53,'Blocker log'!$G:$G,"Hard blocker")) -> 0 | O53: =IF($B53="","",COUNTIFS('Blocker log'!$A:$A,$B53,'Blocker log'!$G:$G,"Hard blocker",'Blocker log'!$L:$L,9)) -> 0 | P53: =IF($B53="","",MAXIFS('Blocker log'!$L:$L,'Blocker log'!$A:$A,$B53,'Blocker log'!$G:$G,"Hard blocker")) -> 0 | Q53: =IF($B53="","",IF($K53<>"Complete","Assessment pending",IF($N53=0,"Ready now",VLOOKUP($P53,Lists!$D$2:$E$5,2,FALSE)))) -> Assessment pending
A54: 0017000000qySf5AAE | B54: Adani Enterprises Limited | C54: Tier 2 | D54: JAPAC | E54: India | F54: India Conglomerates and SP | G54: Cohort 1: Upgrades in progress | M54: =IF($B54="","",COUNTIFS('Blocker log'!$A:$A,$B54,'Blocker log'!$G:$G,"<>")) -> 0 | N54: =IF($B54="","",COUNTIFS('Blocker log'!$A:$A,$B54,'Blocker log'!$G:$G,"Hard blocker")) -> 0 | O54: =IF($B54="","",COUNTIFS('Blocker log'!$A:$A,$B54,'Blocker log'!$G:$G,"Hard blocker",'Blocker log'!$L:$L,9)) -> 0 | P54: =IF($B54="","",MAXIFS('Blocker log'!$L:$L,'Blocker log'!$A:$A,$B54,'Blocker log'!$G:$G,"Hard blocker")) -> 0 | Q54: =IF($B54="","",IF($K54<>"Complete","Assessment pending",IF($N54=0,"Ready now",VLOOKUP($P54,Lists!$D$2:$E$5,2,FALSE)))) -> Assessment pending
A55: 0017000000pdPvnAAE | B55: Nationwide Building Society | C55: Tier 1 | D55: EMEA | E55: UKI | F55: UK Strategic | G55: Cohort 1: Upgrades in progress | H55: 441946 | I55: Neel Dave | K55: Pending | M55: =IF($B55="","",COUNTIFS('Blocker log'!$A:$A,$B55,'Blocker log'!$G:$G,"<>")) -> 0 | N55: =IF($B55="","",COUNTIFS('Blocker log'!$A:$A,$B55,'Blocker log'!$G:$G,"Hard blocker")) -> 0 | O55: =IF($B55="","",COUNTIFS('Blocker log'!$A:$A,$B55,'Blocker log'!$G:$G,"Hard blocker",'Blocker log'!$L:$L,9)) -> 0 | P55: =IF($B55="","",MAXIFS('Blocker log'!$L:$L,'Blocker log'!$A:$A,$B55,'Blocker log'!$G:$G,"Hard blocker")) -> 0 | Q55: =IF($B55="","",IF($K55<>"Complete","Assessment pending",IF($N55=0,"Ready now",VLOOKUP($P55,Lists!$D$2:$E$5,2,FALSE)))) -> Assessment pending
A56: 0014u00001mrMwXAAU | B56: Nippon Life Insurance Australia and New Zealand Limited | C56: Tier 2 | D56: JAPAC | E56: ANZ | F56: ANZ East Coast Majors | G56: Cohort 1: Upgrades in progress | H56: 214458 | M56: =IF($B56="","",COUNTIFS('Blocker log'!$A:$A,$B56,'Blocker log'!$G:$G,"<>")) -> 0 | N56: =IF($B56="","",COUNTIFS('Blocker log'!$A:$A,$B56,'Blocker log'!$G:$G,"Hard blocker")) -> 0 | O56: =IF($B56="","",COUNTIFS('Blocker log'!$A:$A,$B56,'Blocker log'!$G:$G,"Hard blocker",'Blocker log'!$L:$L,9)) -> 0 | P56: =IF($B56="","",MAXIFS('Blocker log'!$L:$L,'Blocker log'!$A:$A,$B56,'Blocker log'!$G:$G,"Hard blocker")) -> 0 | Q56: =IF($B56="","",IF($K56<>"Complete","Assessment pending",IF($N56=0,"Ready now",VLOOKUP($P56,Lists!$D$2:$E$5,2,FALSE)))) -> Assessment pending
A57: 0014u00001yJ3tHAAS | B57: Volkswagen Software Asset Management GmbH | C57: Tier 1 | D57: EMEA | E57: Germany | F57: Germany Strategic | G57: Cohort 1: Upgrades in progress | H57: 1794185 | I57: Oleg Fiksel | K57: Pending | M57: =IF($B57="","",COUNTIFS('Blocker log'!$A:$A,$B57,'Blocker log'!$G:$G,"<>")) -> 0 | N57: =IF($B57="","",COUNTIFS('Blocker log'!$A:$A,$B57,'Blocker log'!$G:$G,"Hard blocker")) -> 0 | O57: =IF($B57="","",COUNTIFS('Blocker log'!$A:$A,$B57,'Blocker log'!$G:$G,"Hard blocker",'Blocker log'!$L:$L,9)) -> 0 | P57: =IF($B57="","",MAXIFS('Blocker log'!$L:$L,'Blocker log'!$A:$A,$B57,'Blocker log'!$G:$G,"Hard blocker")) -> 0 | Q57: =IF($B57="","",IF($K57<>"Complete","Assessment pending",IF($N57=0,"Ready now",VLOOKUP($P57,Lists!$D$2:$E$5,2,FALSE)))) -> Assessment pending
A58: 0017000000YweyvAAB | B58: Murata Manufacturing Co., Ltd. | C58: Tier 2 | D58: JAPAC | E58: JP | F58: JP Majors 2 | G58: Cohort 1: Upgrades in progress | H58: 223538 | M58: =IF($B58="","",COUNTIFS('Blocker log'!$A:$A,$B58,'Blocker log'!$G:$G,"<>")) -> 0 | N58: =IF($B58="","",COUNTIFS('Blocker log'!$A:$A,$B58,'Blocker log'!$G:$G,"Hard blocker")) -> 0 | O58: =IF($B58="","",COUNTIFS('Blocker log'!$A:$A,$B58,'Blocker log'!$G:$G,"Hard blocker",'Blocker log'!$L:$L,9)) -> 0 | P58: =IF($B58="","",MAXIFS('Blocker log'!$L:$L,'Blocker log'!$A:$A,$B58,'Blocker log'!$G:$G,"Hard blocker")) -> 0 | Q58: =IF($B58="","",IF($K58<>"Complete","Assessment pending",IF($N58=0,"Ready now",VLOOKUP($P58,Lists!$D$2:$E$5,2,FALSE)))) -> Assessment pending
A59: 0017000000nylXCAAY | B59: Admiral Group Plc | C59: Tier 2 | D59: EMEA | E59: UKI | F59: UK Majors | G59: Cohort 1: Upgrades in progress | H59: 432295 | M59: =IF($B59="","",COUNTIFS('Blocker log'!$A:$A,$B59,'Blocker log'!$G:$G,"<>")) -> 0 | N59: =IF($B59="","",COUNTIFS('Blocker log'!$A:$A,$B59,'Blocker log'!$G:$G,"Hard blocker")) -> 0 | O59: =IF($B59="","",COUNTIFS('Blocker log'!$A:$A,$B59,'Blocker log'!$G:$G,"Hard blocker",'Blocker log'!$L:$L,9)) -> 0 | P59: =IF($B59="","",MAXIFS('Blocker log'!$L:$L,'Blocker log'!$A:$A,$B59,'Blocker log'!$G:$G,"Hard blocker")) -> 0 | Q59: =IF($B59="","",IF($K59<>"Complete","Assessment pending",IF($N59=0,"Ready now",VLOOKUP($P59,Lists!$D$2:$E$5,2,FALSE)))) -> Assessment pending
A60: 0017000000nyW8xAAE | B60: MAPFRE S.A | C60: Tier 2 | D60: EMEA | E60: Iberia | F60: Spain Private | G60: Cohort 1: Upgrades in progress | H60: 432414 | M60: =IF($B60="","",COUNTIFS('Blocker log'!$A:$A,$B60,'Blocker log'!$G:$G,"<>")) -> 0 | N60: =IF($B60="","",COUNTIFS('Blocker log'!$A:$A,$B60,'Blocker log'!$G:$G,"Hard blocker")) -> 0 | O60: =IF($B60="","",COUNTIFS('Blocker log'!$A:$A,$B60,'Blocker log'!$G:$G,"Hard blocker",'Blocker log'!$L:$L,9)) -> 0 | P60: =IF($B60="","",MAXIFS('Blocker log'!$L:$L,'Blocker log'!$A:$A,$B60,'Blocker log'!$G:$G,"Hard blocker")) -> 0 | Q60: =IF($B60="","",IF($K60<>"Complete","Assessment pending",IF($N60=0,"Ready now",VLOOKUP($P60,Lists!$D$2:$E$5,2,FALSE)))) -> Assessment pending
A61: 0017000000qySkiAAE | B61: EDP Global | C61: Tier 2 | D61: EMEA | E61: Iberia | F61: Portugal | G61: Cohort 1: Upgrades in progress | H61: 227991 | M61: =IF($B61="","",COUNTIFS('Blocker log'!$A:$A,$B61,'Blocker log'!$G:$G,"<>")) -> 0 | N61: =IF($B61="","",COUNTIFS('Blocker log'!$A:$A,$B61,'Blocker log'!$G:$G,"Hard blocker")) -> 0 | O61: =IF($B61="","",COUNTIFS('Blocker log'!$A:$A,$B61,'Blocker log'!$G:$G,"Hard blocker",'Blocker log'!$L:$L,9)) -> 0 | P61: =IF($B61="","",MAXIFS('Blocker log'!$L:$L,'Blocker log'!$A:$A,$B61,'Blocker log'!$G:$G,"Hard blocker")) -> 0 | Q61: =IF($B61="","",IF($K61<>"Complete","Assessment pending",IF($N61=0,"Ready now",VLOOKUP($P61,Lists!$D$2:$E$5,2,FALSE)))) -> Assessment pending
A62: 0017000001ITp6fAAD | B62: Rakuten Usa, Inc. | C62: Tier 2 | D62: AMER | E62: AMER Commercial | F62: SMB | G62: Cohort 1: Upgrades in progress | H62: 425742 | M62: =IF($B62="","",COUNTIFS('Blocker log'!$A:$A,$B62,'Blocker log'!$G:$G,"<>")) -> 0 | N62: =IF($B62="","",COUNTIFS('Blocker log'!$A:$A,$B62,'Blocker log'!$G:$G,"Hard blocker")) -> 0 | O62: =IF($B62="","",COUNTIFS('Blocker log'!$A:$A,$B62,'Blocker log'!$G:$G,"Hard blocker",'Blocker log'!$L:$L,9)) -> 0 | P62: =IF($B62="","",MAXIFS('Blocker log'!$L:$L,'Blocker log'!$A:$A,$B62,'Blocker log'!$G:$G,"Hard blocker")) -> 0 | Q62: =IF($B62="","",IF($K62<>"Complete","Assessment pending",IF($N62=0,"Ready now",VLOOKUP($P62,Lists!$D$2:$E$5,2,FALSE)))) -> Assessment pending
A63: 0014u000027qiy4AAA | B63: Fed-Jasmine5 | C63: Tier 2 | D63: AMER | E63: US Public Sector | F63: Civilian/FSI | G63: Cohort 1: Upgrades in progress | H63: 421167 | M63: =IF($B63="","",COUNTIFS('Blocker log'!$A:$A,$B63,'Blocker log'!$G:$G,"<>")) -> 0 | N63: =IF($B63="","",COUNTIFS('Blocker log'!$A:$A,$B63,'Blocker log'!$G:$G,"Hard blocker")) -> 0 | O63: =IF($B63="","",COUNTIFS('Blocker log'!$A:$A,$B63,'Blocker log'!$G:$G,"Hard blocker",'Blocker log'!$L:$L,9)) -> 0 | P63: =IF($B63="","",MAXIFS('Blocker log'!$L:$L,'Blocker log'!$A:$A,$B63,'Blocker log'!$G:$G,"Hard blocker")) -> 0 | Q63: =IF($B63="","",IF($K63<>"Complete","Assessment pending",IF($N63=0,"Ready now",VLOOKUP($P63,Lists!$D$2:$E$5,2,FALSE)))) -> Assessment pending
A64: 0017000000PP73xAAD | B64: Freddie Mac | C64: Tier 1 | D64: AMER | E64: AMER Strategic East | F64: AMER Strategic East MidAtlantic | G64: Cohort 1: Upgrades in progress | H64: 107136 | I64: Ravi Badana | K64: Pending | M64: =IF($B64="","",COUNTIFS('Blocker log'!$A:$A,$B64,'Blocker log'!$G:$G,"<>")) -> 0 | N64: =IF($B64="","",COUNTIFS('Blocker log'!$A:$A,$B64,'Blocker log'!$G:$G,"Hard blocker")) -> 0 | O64: =IF($B64="","",COUNTIFS('Blocker log'!$A:$A,$B64,'Blocker log'!$G:$G,"Hard blocker",'Blocker log'!$L:$L,9)) -> 0 | P64: =IF($B64="","",MAXIFS('Blocker log'!$L:$L,'Blocker log'!$A:$A,$B64,'Blocker log'!$G:$G,"Hard blocker")) -> 0 | Q64: =IF($B64="","",IF($K64<>"Complete","Assessment pending",IF($N64=0,"Ready now",VLOOKUP($P64,Lists!$D$2:$E$5,2,FALSE)))) -> Assessment pending
A65: 0017000000nylpAAAQ | B65: Whitbread | C65: Tier 2 | D65: EMEA | E65: UKI | F65: UK Majors | G65: Cohort 1: Upgrades in progress | H65: 413281 | M65: =IF($B65="","",COUNTIFS('Blocker log'!$A:$A,$B65,'Blocker log'!$G:$G,"<>")) -> 0 | N65: =IF($B65="","",COUNTIFS('Blocker log'!$A:$A,$B65,'Blocker log'!$G:$G,"Hard blocker")) -> 0 | O65: =IF($B65="","",COUNTIFS('Blocker log'!$A:$A,$B65,'Blocker log'!$G:$G,"Hard blocker",'Blocker log'!$L:$L,9)) -> 0 | P65: =IF($B65="","",MAXIFS('Blocker log'!$L:$L,'Blocker log'!$A:$A,$B65,'Blocker log'!$G:$G,"Hard blocker")) -> 0 | Q65: =IF($B65="","",IF($K65<>"Complete","Assessment pending",IF($N65=0,"Ready now",VLOOKUP($P65,Lists!$D$2:$E$5,2,FALSE)))) -> Assessment pending
A66: 0014u00001x8IUDAA2 | B66: Dyson Operations Pte. Ltd. | C66: Tier 2 | D66: JAPAC | E66: ASEAN | F66: Singapore | G66: Cohort 1: Upgrades in progress | H66: 206367 | M66: =IF($B66="","",COUNTIFS('Blocker log'!$A:$A,$B66,'Blocker log'!$G:$G,"<>")) -> 0 | N66: =IF($B66="","",COUNTIFS('Blocker log'!$A:$A,$B66,'Blocker log'!$G:$G,"Hard blocker")) -> 0 | O66: =IF($B66="","",COUNTIFS('Blocker log'!$A:$A,$B66,'Blocker log'!$G:$G,"Hard blocker",'Blocker log'!$L:$L,9)) -> 0 | P66: =IF($B66="","",MAXIFS('Blocker log'!$L:$L,'Blocker log'!$A:$A,$B66,'Blocker log'!$G:$G,"Hard blocker")) -> 0 | Q66: =IF($B66="","",IF($K66<>"Complete","Assessment pending",IF($N66=0,"Ready now",VLOOKUP($P66,Lists!$D$2:$E$5,2,FALSE)))) -> Assessment pending
A67: 0017000000nesZZAAY | B67: Amp Limited | C67: Tier 2 | D67: JAPAC | E67: ANZ | F67: ANZ East Coast Majors | G67: Cohort 1: Upgrades in progress | H67: 174291 | M67: =IF($B67="","",COUNTIFS('Blocker log'!$A:$A,$B67,'Blocker log'!$G:$G,"<>")) -> 0 | N67: =IF($B67="","",COUNTIFS('Blocker log'!$A:$A,$B67,'Blocker log'!$G:$G,"Hard blocker")) -> 0 | O67: =IF($B67="","",COUNTIFS('Blocker log'!$A:$A,$B67,'Blocker log'!$G:$G,"Hard blocker",'Blocker log'!$L:$L,9)) -> 0 | P67: =IF($B67="","",MAXIFS('Blocker log'!$L:$L,'Blocker log'!$A:$A,$B67,'Blocker log'!$G:$G,"Hard blocker")) -> 0 | Q67: =IF($B67="","",IF($K67<>"Complete","Assessment pending",IF($N67=0,"Ready now",VLOOKUP($P67,Lists!$D$2:$E$5,2,FALSE)))) -> Assessment pending
A68: 0014u00001tDTyIAAW | B68: Ataccama Software, s.r.o. | C68: Tier 2 | D68: EMEA | E68: CEE | F68: Central EEUR | G68: Cohort 1: Upgrades in progress | H68: 20000 | M68: =IF($B68="","",COUNTIFS('Blocker log'!$A:$A,$B68,'Blocker log'!$G:$G,"<>")) -> 0 | N68: =IF($B68="","",COUNTIFS('Blocker log'!$A:$A,$B68,'Blocker log'!$G:$G,"Hard blocker")) -> 0 | O68: =IF($B68="","",COUNTIFS('Blocker log'!$A:$A,$B68,'Blocker log'!$G:$G,"Hard blocker",'Blocker log'!$L:$L,9)) -> 0 | P68: =IF($B68="","",MAXIFS('Blocker log'!$L:$L,'Blocker log'!$A:$A,$B68,'Blocker log'!$G:$G,"Hard blocker")) -> 0 | Q68: =IF($B68="","",IF($K68<>"Complete","Assessment pending",IF($N68=0,"Ready now",VLOOKUP($P68,Lists!$D$2:$E$5,2,FALSE)))) -> Assessment pending
A69: 0017000000qyShCAAU | B69: Bancolombia S.A. | C69: Tier 2 | D69: LATAM | E69: MCA North | F69: MCA North | G69: Cohort 1: Upgrades in progress | H69: 338356 | M69: =IF($B69="","",COUNTIFS('Blocker log'!$A:$A,$B69,'Blocker log'!$G:$G,"<>")) -> 0 | N69: =IF($B69="","",COUNTIFS('Blocker log'!$A:$A,$B69,'Blocker log'!$G:$G,"Hard blocker")) -> 0 | O69: =IF($B69="","",COUNTIFS('Blocker log'!$A:$A,$B69,'Blocker log'!$G:$G,"Hard blocker",'Blocker log'!$L:$L,9)) -> 0 | P69: =IF($B69="","",MAXIFS('Blocker log'!$L:$L,'Blocker log'!$A:$A,$B69,'Blocker log'!$G:$G,"Hard blocker")) -> 0 | Q69: =IF($B69="","",IF($K69<>"Complete","Assessment pending",IF($N69=0,"Ready now",VLOOKUP($P69,Lists!$D$2:$E$5,2,FALSE)))) -> Assessment pending
A70: 0017000000qx7kfAAA | B70: Fidelity National Financial, Inc. | C70: Tier 1 | D70: AMER | E70: AMER Strategic East | F70: AMER Strategic East Southeast | G70: Cohort 1: Upgrades in progress | H70: 1483675 | I70: Ravi Badana | K70: Pending | M70: =IF($B70="","",COUNTIFS('Blocker log'!$A:$A,$B70,'Blocker log'!$G:$G,"<>")) -> 0 | N70: =IF($B70="","",COUNTIFS('Blocker log'!$A:$A,$B70,'Blocker log'!$G:$G,"Hard blocker")) -> 0 | O70: =IF($B70="","",COUNTIFS('Blocker log'!$A:$A,$B70,'Blocker log'!$G:$G,"Hard blocker",'Blocker log'!$L:$L,9)) -> 0 | P70: =IF($B70="","",MAXIFS('Blocker log'!$L:$L,'Blocker log'!$A:$A,$B70,'Blocker log'!$G:$G,"Hard blocker")) -> 0 | Q70: =IF($B70="","",IF($K70<>"Complete","Assessment pending",IF($N70=0,"Ready now",VLOOKUP($P70,Lists!$D$2:$E$5,2,FALSE)))) -> Assessment pending
A71: 0010g00001j5zIuAAI | B71: STMicroelectronics | C71: Tier 2 | D71: EMEA | E71: France | F71: France Strategic | G71: Cohort 1: Upgrades in progress | H71: 388943 | M71: =IF($B71="","",COUNTIFS('Blocker log'!$A:$A,$B71,'Blocker log'!$G:$G,"<>")) -> 0 | N71: =IF($B71="","",COUNTIFS('Blocker log'!$A:$A,$B71,'Blocker log'!$G:$G,"Hard blocker")) -> 0 | O71: =IF($B71="","",COUNTIFS('Blocker log'!$A:$A,$B71,'Blocker log'!$G:$G,"Hard blocker",'Blocker log'!$L:$L,9)) -> 0 | P71: =IF($B71="","",MAXIFS('Blocker log'!$L:$L,'Blocker log'!$A:$A,$B71,'Blocker log'!$G:$G,"Hard blocker")) -> 0 | Q71: =IF($B71="","",IF($K71<>"Complete","Assessment pending",IF($N71=0,"Ready now",VLOOKUP($P71,Lists!$D$2:$E$5,2,FALSE)))) -> Assessment pending
A72: 0017000001RMDCFAA5 | B72: The Pokemon Company International Inc | C72: Tier 2 | D72: AMER | E72: AMER Commercial | F72: Select West | G72: Cohort 1: Upgrades in progress | H72: 386259 | M72: =IF($B72="","",COUNTIFS('Blocker log'!$A:$A,$B72,'Blocker log'!$G:$G,"<>")) -> 0 | N72: =IF($B72="","",COUNTIFS('Blocker log'!$A:$A,$B72,'Blocker log'!$G:$G,"Hard blocker")) -> 0 | O72: =IF($B72="","",COUNTIFS('Blocker log'!$A:$A,$B72,'Blocker log'!$G:$G,"Hard blocker",'Blocker log'!$L:$L,9)) -> 0 | P72: =IF($B72="","",MAXIFS('Blocker log'!$L:$L,'Blocker log'!$A:$A,$B72,'Blocker log'!$G:$G,"Hard blocker")) -> 0 | Q72: =IF($B72="","",IF($K72<>"Complete","Assessment pending",IF($N72=0,"Ready now",VLOOKUP($P72,Lists!$D$2:$E$5,2,FALSE)))) -> Assessment pending
A73: 0014u00001uGbfaAAC | B73: Kyndryl, Inc. | C73: Tier 2 | D73: AMER | E73: AMER Strategic East | F73: AMER Strategic East SI/SP | G73: Cohort 1: Upgrades in progress | H73: 382707 | M73: =IF($B73="","",COUNTIFS('Blocker log'!$A:$A,$B73,'Blocker log'!$G:$G,"<>")) -> 0 | N73: =IF($B73="","",COUNTIFS('Blocker log'!$A:$A,$B73,'Blocker log'!$G:$G,"Hard blocker")) -> 0 | O73: =IF($B73="","",COUNTIFS('Blocker log'!$A:$A,$B73,'Blocker log'!$G:$G,"Hard blocker",'Blocker log'!$L:$L,9)) -> 0 | P73: =IF($B73="","",MAXIFS('Blocker log'!$L:$L,'Blocker log'!$A:$A,$B73,'Blocker log'!$G:$G,"Hard blocker")) -> 0 | Q73: =IF($B73="","",IF($K73<>"Complete","Assessment pending",IF($N73=0,"Ready now",VLOOKUP($P73,Lists!$D$2:$E$5,2,FALSE)))) -> Assessment pending
A74: 0017000000PN6iDAAT | B74: Tyson Foods, Inc. | C74: Tier 1 | D74: AMER | E74: AMER Strategic Central | F74: AMER Strategic Central Texas | G74: Cohort 1: Upgrades in progress | H74: 1069260 | I74: Ravi Badana | K74: Pending | M74: =IF($B74="","",COUNTIFS('Blocker log'!$A:$A,$B74,'Blocker log'!$G:$G,"<>")) -> 0 | N74: =IF($B74="","",COUNTIFS('Blocker log'!$A:$A,$B74,'Blocker log'!$G:$G,"Hard blocker")) -> 0 | O74: =IF($B74="","",COUNTIFS('Blocker log'!$A:$A,$B74,'Blocker log'!$G:$G,"Hard blocker",'Blocker log'!$L:$L,9)) -> 0 | P74: =IF($B74="","",MAXIFS('Blocker log'!$L:$L,'Blocker log'!$A:$A,$B74,'Blocker log'!$G:$G,"Hard blocker")) -> 0 | Q74: =IF($B74="","",IF($K74<>"Complete","Assessment pending",IF($N74=0,"Ready now",VLOOKUP($P74,Lists!$D$2:$E$5,2,FALSE)))) -> Assessment pending
A75: 0017000000YfwM2AAJ | B75: A&O Shearman | C75: Tier 2 | D75: EMEA | E75: UKI | F75: UK Majors | G75: Cohort 1: Upgrades in progress | H75: 376770 | M75: =IF($B75="","",COUNTIFS('Blocker log'!$A:$A,$B75,'Blocker log'!$G:$G,"<>")) -> 0 | N75: =IF($B75="","",COUNTIFS('Blocker log'!$A:$A,$B75,'Blocker log'!$G:$G,"Hard blocker")) -> 0 | O75: =IF($B75="","",COUNTIFS('Blocker log'!$A:$A,$B75,'Blocker log'!$G:$G,"Hard blocker",'Blocker log'!$L:$L,9)) -> 0 | P75: =IF($B75="","",MAXIFS('Blocker log'!$L:$L,'Blocker log'!$A:$A,$B75,'Blocker log'!$G:$G,"Hard blocker")) -> 0 | Q75: =IF($B75="","",IF($K75<>"Complete","Assessment pending",IF($N75=0,"Ready now",VLOOKUP($P75,Lists!$D$2:$E$5,2,FALSE)))) -> Assessment pending
A76: 0017000000cIUW0AAO | B76: Intact | C76: Tier 2 | D76: AMER | E76: AMER Canada | F76: Canada East West Commercial | G76: Cohort 1: Upgrades in progress | H76: 443561 | M76: =IF($B76="","",COUNTIFS('Blocker log'!$A:$A,$B76,'Blocker log'!$G:$G,"<>")) -> 0 | N76: =IF($B76="","",COUNTIFS('Blocker log'!$A:$A,$B76,'Blocker log'!$G:$G,"Hard blocker")) -> 0 | O76: =IF($B76="","",COUNTIFS('Blocker log'!$A:$A,$B76,'Blocker log'!$G:$G,"Hard blocker",'Blocker log'!$L:$L,9)) -> 0 | P76: =IF($B76="","",MAXIFS('Blocker log'!$L:$L,'Blocker log'!$A:$A,$B76,'Blocker log'!$G:$G,"Hard blocker")) -> 0 | Q76: =IF($B76="","",IF($K76<>"Complete","Assessment pending",IF($N76=0,"Ready now",VLOOKUP($P76,Lists!$D$2:$E$5,2,FALSE)))) -> Assessment pending
A77: 0017000001NWi6iAAD | B77: PEXA Services Pty Ltd | C77: Tier 2 | D77: JAPAC | E77: ANZ | F77: ANZ East Coast Majors | G77: Cohort 1: Upgrades in progress | H77: 364573 | M77: =IF($B77="","",COUNTIFS('Blocker log'!$A:$A,$B77,'Blocker log'!$G:$G,"<>")) -> 0 | N77: =IF($B77="","",COUNTIFS('Blocker log'!$A:$A,$B77,'Blocker log'!$G:$G,"Hard blocker")) -> 0 | O77: =IF($B77="","",COUNTIFS('Blocker log'!$A:$A,$B77,'Blocker log'!$G:$G,"Hard blocker",'Blocker log'!$L:$L,9)) -> 0 | P77: =IF($B77="","",MAXIFS('Blocker log'!$L:$L,'Blocker log'!$A:$A,$B77,'Blocker log'!$G:$G,"Hard blocker")) -> 0 | Q77: =IF($B77="","",IF($K77<>"Complete","Assessment pending",IF($N77=0,"Ready now",VLOOKUP($P77,Lists!$D$2:$E$5,2,FALSE)))) -> Assessment pending
A78: 0017000000cIF9wAAG | B78: Baring Investment Services Limited | C78: Tier 2 | D78: EMEA | E78: UKI | F78: UK Majors | G78: Cohort 1: Upgrades in progress | H78: 366444 | M78: =IF($B78="","",COUNTIFS('Blocker log'!$A:$A,$B78,'Blocker log'!$G:$G,"<>")) -> 0 | N78: =IF($B78="","",COUNTIFS('Blocker log'!$A:$A,$B78,'Blocker log'!$G:$G,"Hard blocker")) -> 0 | O78: =IF($B78="","",COUNTIFS('Blocker log'!$A:$A,$B78,'Blocker log'!$G:$G,"Hard blocker",'Blocker log'!$L:$L,9)) -> 0 | P78: =IF($B78="","",MAXIFS('Blocker log'!$L:$L,'Blocker log'!$A:$A,$B78,'Blocker log'!$G:$G,"Hard blocker")) -> 0 | Q78: =IF($B78="","",IF($K78<>"Complete","Assessment pending",IF($N78=0,"Ready now",VLOOKUP($P78,Lists!$D$2:$E$5,2,FALSE)))) -> Assessment pending
A79: 0017000000gE2ySAAS | B79: Wawa, Inc. | C79: Tier 2 | D79: AMER | E79: AMER Strategic East | F79: AMER Strategic East MidAtlantic | G79: Cohort 1: Upgrades in progress | H79: 101660 | M79: =IF($B79="","",COUNTIFS('Blocker log'!$A:$A,$B79,'Blocker log'!$G:$G,"<>")) -> 0 | N79: =IF($B79="","",COUNTIFS('Blocker log'!$A:$A,$B79,'Blocker log'!$G:$G,"Hard blocker")) -> 0 | O79: =IF($B79="","",COUNTIFS('Blocker log'!$A:$A,$B79,'Blocker log'!$G:$G,"Hard blocker",'Blocker log'!$L:$L,9)) -> 0 | P79: =IF($B79="","",MAXIFS('Blocker log'!$L:$L,'Blocker log'!$A:$A,$B79,'Blocker log'!$G:$G,"Hard blocker")) -> 0 | Q79: =IF($B79="","",IF($K79<>"Complete","Assessment pending",IF($N79=0,"Ready now",VLOOKUP($P79,Lists!$D$2:$E$5,2,FALSE)))) -> Assessment pending
A80: 0017000000orFxrAAE | B80: Rockwell Automation, Incorporated | C80: Tier 2 | D80: AMER | E80: AMER Strategic Central | F80: AMER Strategic Central Northcentral | G80: Cohort 1: Upgrades in progress | H80: 353220 | M80: =IF($B80="","",COUNTIFS('Blocker log'!$A:$A,$B80,'Blocker log'!$G:$G,"<>")) -> 0 | N80: =IF($B80="","",COUNTIFS('Blocker log'!$A:$A,$B80,'Blocker log'!$G:$G,"Hard blocker")) -> 0 | O80: =IF($B80="","",COUNTIFS('Blocker log'!$A:$A,$B80,'Blocker log'!$G:$G,"Hard blocker",'Blocker log'!$L:$L,9)) -> 0 | P80: =IF($B80="","",MAXIFS('Blocker log'!$L:$L,'Blocker log'!$A:$A,$B80,'Blocker log'!$G:$G,"Hard blocker")) -> 0 | Q80: =IF($B80="","",IF($K80<>"Complete","Assessment pending",IF($N80=0,"Ready now",VLOOKUP($P80,Lists!$D$2:$E$5,2,FALSE)))) -> Assessment pending
A81: 0017000000mAYzCAAW | B81: Sanofi S.A | C81: Tier 2 | D81: EMEA | E81: France | F81: France Strategic | G81: Cohort 1: Upgrades in progress | H81: 352512 | M81: =IF($B81="","",COUNTIFS('Blocker log'!$A:$A,$B81,'Blocker log'!$G:$G,"<>")) -> 0 | N81: =IF($B81="","",COUNTIFS('Blocker log'!$A:$A,$B81,'Blocker log'!$G:$G,"Hard blocker")) -> 0 | O81: =IF($B81="","",COUNTIFS('Blocker log'!$A:$A,$B81,'Blocker log'!$G:$G,"Hard blocker",'Blocker log'!$L:$L,9)) -> 0 | P81: =IF($B81="","",MAXIFS('Blocker log'!$L:$L,'Blocker log'!$A:$A,$B81,'Blocker log'!$G:$G,"Hard blocker")) -> 0 | Q81: =IF($B81="","",IF($K81<>"Complete","Assessment pending",IF($N81=0,"Ready now",VLOOKUP($P81,Lists!$D$2:$E$5,2,FALSE)))) -> Assessment pending
A82: 0017000000y1HbLAAU | B82: Hilton Worldwide Holdings Inc. | C82: Tier 1 | D82: AMER | E82: AMER Strategic Central | F82: AMER Strategic Central Central Plains | G82: Cohort 1: Upgrades in progress | H82: 203435 | I82: Ravi Badana | K82: Pending | M82: =IF($B82="","",COUNTIFS('Blocker log'!$A:$A,$B82,'Blocker log'!$G:$G,"<>")) -> 0 | N82: =IF($B82="","",COUNTIFS('Blocker log'!$A:$A,$B82,'Blocker log'!$G:$G,"Hard blocker")) -> 0 | O82: =IF($B82="","",COUNTIFS('Blocker log'!$A:$A,$B82,'Blocker log'!$G:$G,"Hard blocker",'Blocker log'!$L:$L,9)) -> 0 | P82: =IF($B82="","",MAXIFS('Blocker log'!$L:$L,'Blocker log'!$A:$A,$B82,'Blocker log'!$G:$G,"Hard blocker")) -> 0 | Q82: =IF($B82="","",IF($K82<>"Complete","Assessment pending",IF($N82=0,"Ready now",VLOOKUP($P82,Lists!$D$2:$E$5,2,FALSE)))) -> Assessment pending
A83: 0014u000026KaSRAA0 | B83: Malaysia Aviation Group Berhad | C83: Tier 2 | D83: JAPAC | E83: ASEAN | F83: Malaysia | G83: Cohort 1: Upgrades in progress | H83: 330494 | M83: =IF($B83="","",COUNTIFS('Blocker log'!$A:$A,$B83,'Blocker log'!$G:$G,"<>")) -> 0 | N83: =IF($B83="","",COUNTIFS('Blocker log'!$A:$A,$B83,'Blocker log'!$G:$G,"Hard blocker")) -> 0 | O83: =IF($B83="","",COUNTIFS('Blocker log'!$A:$A,$B83,'Blocker log'!$G:$G,"Hard blocker",'Blocker log'!$L:$L,9)) -> 0 | P83: =IF($B83="","",MAXIFS('Blocker log'!$L:$L,'Blocker log'!$A:$A,$B83,'Blocker log'!$G:$G,"Hard blocker")) -> 0 | Q83: =IF($B83="","",IF($K83<>"Complete","Assessment pending",IF($N83=0,"Ready now",VLOOKUP($P83,Lists!$D$2:$E$5,2,FALSE)))) -> Assessment pending
A84: 0017000001GFR0OAAX | B84: Banco Pichincha C.A. | C84: Tier 2 | D84: LATAM | E84: MCA North | F84: MCA North | G84: Cohort 1: Upgrades in progress | H84: 318060 | M84: =IF($B84="","",COUNTIFS('Blocker log'!$A:$A,$B84,'Blocker log'!$G:$G,"<>")) -> 0 | N84: =IF($B84="","",COUNTIFS('Blocker log'!$A:$A,$B84,'Blocker log'!$G:$G,"Hard blocker")) -> 0 | O84: =IF($B84="","",COUNTIFS('Blocker log'!$A:$A,$B84,'Blocker log'!$G:$G,"Hard blocker",'Blocker log'!$L:$L,9)) -> 0 | P84: =IF($B84="","",MAXIFS('Blocker log'!$L:$L,'Blocker log'!$A:$A,$B84,'Blocker log'!$G:$G,"Hard blocker")) -> 0 | Q84: =IF($B84="","",IF($K84<>"Complete","Assessment pending",IF($N84=0,"Ready now",VLOOKUP($P84,Lists!$D$2:$E$5,2,FALSE)))) -> Assessment pending
A85: 0017000000yNYy4AAG | B85: Yardi Systems, Inc. | C85: Tier 2 | D85: AMER | E85: AMER Strategic West | F85: AMER Strategic West SoCal | G85: Cohort 1: Upgrades in progress | H85: 315725 | M85: =IF($B85="","",COUNTIFS('Blocker log'!$A:$A,$B85,'Blocker log'!$G:$G,"<>")) -> 0 | N85: =IF($B85="","",COUNTIFS('Blocker log'!$A:$A,$B85,'Blocker log'!$G:$G,"Hard blocker")) -> 0 | O85: =IF($B85="","",COUNTIFS('Blocker log'!$A:$A,$B85,'Blocker log'!$G:$G,"Hard blocker",'Blocker log'!$L:$L,9)) -> 0 | P85: =IF($B85="","",MAXIFS('Blocker log'!$L:$L,'Blocker log'!$A:$A,$B85,'Blocker log'!$G:$G,"Hard blocker")) -> 0 | Q85: =IF($B85="","",IF($K85<>"Complete","Assessment pending",IF($N85=0,"Ready now",VLOOKUP($P85,Lists!$D$2:$E$5,2,FALSE)))) -> Assessment pending
A86: 0017000000ylwVDAAY | B86: IVECO SPA | C86: Tier 2 | D86: EMEA | E86: Italy | F86: Italy Private | G86: Cohort 1: Upgrades in progress | H86: 315297 | M86: =IF($B86="","",COUNTIFS('Blocker log'!$A:$A,$B86,'Blocker log'!$G:$G,"<>")) -> 0 | N86: =IF($B86="","",COUNTIFS('Blocker log'!$A:$A,$B86,'Blocker log'!$G:$G,"Hard blocker")) -> 0 | O86: =IF($B86="","",COUNTIFS('Blocker log'!$A:$A,$B86,'Blocker log'!$G:$G,"Hard blocker",'Blocker log'!$L:$L,9)) -> 0 | P86: =IF($B86="","",MAXIFS('Blocker log'!$L:$L,'Blocker log'!$A:$A,$B86,'Blocker log'!$G:$G,"Hard blocker")) -> 0 | Q86: =IF($B86="","",IF($K86<>"Complete","Assessment pending",IF($N86=0,"Ready now",VLOOKUP($P86,Lists!$D$2:$E$5,2,FALSE)))) -> Assessment pending
A87: 001700000137YtQAAU | B87: Tata Consultancy Services Limited | C87: Tier 2 | D87: JAPAC | E87: India | F87: India IT - ITES | G87: Cohort 1: Upgrades in progress | H87: 187210 | M87: =IF($B87="","",COUNTIFS('Blocker log'!$A:$A,$B87,'Blocker log'!$G:$G,"<>")) -> 0 | N87: =IF($B87="","",COUNTIFS('Blocker log'!$A:$A,$B87,'Blocker log'!$G:$G,"Hard blocker")) -> 0 | O87: =IF($B87="","",COUNTIFS('Blocker log'!$A:$A,$B87,'Blocker log'!$G:$G,"Hard blocker",'Blocker log'!$L:$L,9)) -> 0 | P87: =IF($B87="","",MAXIFS('Blocker log'!$L:$L,'Blocker log'!$A:$A,$B87,'Blocker log'!$G:$G,"Hard blocker")) -> 0 | Q87: =IF($B87="","",IF($K87<>"Complete","Assessment pending",IF($N87=0,"Ready now",VLOOKUP($P87,Lists!$D$2:$E$5,2,FALSE)))) -> Assessment pending
A88: 0017000000zfLmuAAE | B88: Union of European Football Associations (UEFA) | C88: Tier 2 | D88: EMEA | E88: Alps | F88: Switzerland/Austria | G88: Cohort 1: Upgrades in progress | H88: 311744 | M88: =IF($B88="","",COUNTIFS('Blocker log'!$A:$A,$B88,'Blocker log'!$G:$G,"<>")) -> 0 | N88: =IF($B88="","",COUNTIFS('Blocker log'!$A:$A,$B88,'Blocker log'!$G:$G,"Hard blocker")) -> 0 | O88: =IF($B88="","",COUNTIFS('Blocker log'!$A:$A,$B88,'Blocker log'!$G:$G,"Hard blocker",'Blocker log'!$L:$L,9)) -> 0 | P88: =IF($B88="","",MAXIFS('Blocker log'!$L:$L,'Blocker log'!$A:$A,$B88,'Blocker log'!$G:$G,"Hard blocker")) -> 0 | Q88: =IF($B88="","",IF($K88<>"Complete","Assessment pending",IF($N88=0,"Ready now",VLOOKUP($P88,Lists!$D$2:$E$5,2,FALSE)))) -> Assessment pending
A89: 0017000001XPurFAAT | B89: Stone Pagamentos S.a. | C89: Tier 2 | D89: LATAM | E89: Brazil | F89: Brazil | G89: Cohort 1: Upgrades in progress | H89: 443998 | M89: =IF($B89="","",COUNTIFS('Blocker log'!$A:$A,$B89,'Blocker log'!$G:$G,"<>")) -> 0 | N89: =IF($B89="","",COUNTIFS('Blocker log'!$A:$A,$B89,'Blocker log'!$G:$G,"Hard blocker")) -> 0 | O89: =IF($B89="","",COUNTIFS('Blocker log'!$A:$A,$B89,'Blocker log'!$G:$G,"Hard blocker",'Blocker log'!$L:$L,9)) -> 0 | P89: =IF($B89="","",MAXIFS('Blocker log'!$L:$L,'Blocker log'!$A:$A,$B89,'Blocker log'!$G:$G,"Hard blocker")) -> 0 | Q89: =IF($B89="","",IF($K89<>"Complete","Assessment pending",IF($N89=0,"Ready now",VLOOKUP($P89,Lists!$D$2:$E$5,2,FALSE)))) -> Assessment pending
A90: 00170000011uEWiAAM | B90: CRISIL LIMITED | C90: Tier 2 | D90: JAPAC | E90: India | F90: India BFSI | G90: Cohort 1: Upgrades in progress | H90: 97271 | M90: =IF($B90="","",COUNTIFS('Blocker log'!$A:$A,$B90,'Blocker log'!$G:$G,"<>")) -> 0 | N90: =IF($B90="","",COUNTIFS('Blocker log'!$A:$A,$B90,'Blocker log'!$G:$G,"Hard blocker")) -> 0 | O90: =IF($B90="","",COUNTIFS('Blocker log'!$A:$A,$B90,'Blocker log'!$G:$G,"Hard blocker",'Blocker log'!$L:$L,9)) -> 0 | P90: =IF($B90="","",MAXIFS('Blocker log'!$L:$L,'Blocker log'!$A:$A,$B90,'Blocker log'!$G:$G,"Hard blocker")) -> 0 | Q90: =IF($B90="","",IF($K90<>"Complete","Assessment pending",IF($N90=0,"Ready now",VLOOKUP($P90,Lists!$D$2:$E$5,2,FALSE)))) -> Assessment pending
A91: 0010g00001j5KivAAE | B91: Canada Pension Plan Investment Board | C91: Tier 2 | D91: AMER | E91: AMER Canada | F91: Canada Public Sector | G91: Cohort 1: Upgrades in progress | H91: 302500 | M91: =IF($B91="","",COUNTIFS('Blocker log'!$A:$A,$B91,'Blocker log'!$G:$G,"<>")) -> 0 | N91: =IF($B91="","",COUNTIFS('Blocker log'!$A:$A,$B91,'Blocker log'!$G:$G,"Hard blocker")) -> 0 | O91: =IF($B91="","",COUNTIFS('Blocker log'!$A:$A,$B91,'Blocker log'!$G:$G,"Hard blocker",'Blocker log'!$L:$L,9)) -> 0 | P91: =IF($B91="","",MAXIFS('Blocker log'!$L:$L,'Blocker log'!$A:$A,$B91,'Blocker log'!$G:$G,"Hard blocker")) -> 0 | Q91: =IF($B91="","",IF($K91<>"Complete","Assessment pending",IF($N91=0,"Ready now",VLOOKUP($P91,Lists!$D$2:$E$5,2,FALSE)))) -> Assessment pending
A92: 0017000001RLJkdAAH | B92: California Employment Development Department | C92: Tier 2 | D92: AMER | E92: US Public Sector | F92: SLED West | G92: Cohort 1: Upgrades in progress | H92: 292000 | M92: =IF($B92="","",COUNTIFS('Blocker log'!$A:$A,$B92,'Blocker log'!$G:$G,"<>")) -> 0 | N92: =IF($B92="","",COUNTIFS('Blocker log'!$A:$A,$B92,'Blocker log'!$G:$G,"Hard blocker")) -> 0 | O92: =IF($B92="","",COUNTIFS('Blocker log'!$A:$A,$B92,'Blocker log'!$G:$G,"Hard blocker",'Blocker log'!$L:$L,9)) -> 0 | P92: =IF($B92="","",MAXIFS('Blocker log'!$L:$L,'Blocker log'!$A:$A,$B92,'Blocker log'!$G:$G,"Hard blocker")) -> 0 | Q92: =IF($B92="","",IF($K92<>"Complete","Assessment pending",IF($N92=0,"Ready now",VLOOKUP($P92,Lists!$D$2:$E$5,2,FALSE)))) -> Assessment pending
A93: 0010g00001lRVosAAG | B93: Porto Seguro Seguro Saude S/A | C93: Tier 1 | D93: LATAM | E93: Brazil | F93: Brazil | G93: Cohort 1: Upgrades in progress | H93: 785724 | M93: =IF($B93="","",COUNTIFS('Blocker log'!$A:$A,$B93,'Blocker log'!$G:$G,"<>")) -> 0 | N93: =IF($B93="","",COUNTIFS('Blocker log'!$A:$A,$B93,'Blocker log'!$G:$G,"Hard blocker")) -> 0 | O93: =IF($B93="","",COUNTIFS('Blocker log'!$A:$A,$B93,'Blocker log'!$G:$G,"Hard blocker",'Blocker log'!$L:$L,9)) -> 0 | P93: =IF($B93="","",MAXIFS('Blocker log'!$L:$L,'Blocker log'!$A:$A,$B93,'Blocker log'!$G:$G,"Hard blocker")) -> 0 | Q93: =IF($B93="","",IF($K93<>"Complete","Assessment pending",IF($N93=0,"Ready now",VLOOKUP($P93,Lists!$D$2:$E$5,2,FALSE)))) -> Assessment pending
A94: 0017000000qySs8AAE | B94: PPG Industries, Inc. | C94: Tier 2 | D94: AMER | E94: AMER Strategic Central | F94: AMER Strategic Central Ohio Valley | G94: Cohort 1: Upgrades in progress | H94: 34948 | M94: =IF($B94="","",COUNTIFS('Blocker log'!$A:$A,$B94,'Blocker log'!$G:$G,"<>")) -> 0 | N94: =IF($B94="","",COUNTIFS('Blocker log'!$A:$A,$B94,'Blocker log'!$G:$G,"Hard blocker")) -> 0 | O94: =IF($B94="","",COUNTIFS('Blocker log'!$A:$A,$B94,'Blocker log'!$G:$G,"Hard blocker",'Blocker log'!$L:$L,9)) -> 0 | P94: =IF($B94="","",MAXIFS('Blocker log'!$L:$L,'Blocker log'!$A:$A,$B94,'Blocker log'!$G:$G,"Hard blocker")) -> 0 | Q94: =IF($B94="","",IF($K94<>"Complete","Assessment pending",IF($N94=0,"Ready now",VLOOKUP($P94,Lists!$D$2:$E$5,2,FALSE)))) -> Assessment pending
A95: 0017000000gF8DtAAK | B95: Abbott Laboratories | C95: Tier 1 | D95: AMER | E95: AMER Strategic Central | F95: AMER Strategic Central Northcentral | G95: Cohort 1: Upgrades in progress | H95: 807369 | I95: Ravi Badana | K95: Pending | M95: =IF($B95="","",COUNTIFS('Blocker log'!$A:$A,$B95,'Blocker log'!$G:$G,"<>")) -> 0 | N95: =IF($B95="","",COUNTIFS('Blocker log'!$A:$A,$B95,'Blocker log'!$G:$G,"Hard blocker")) -> 0 | O95: =IF($B95="","",COUNTIFS('Blocker log'!$A:$A,$B95,'Blocker log'!$G:$G,"Hard blocker",'Blocker log'!$L:$L,9)) -> 0 | P95: =IF($B95="","",MAXIFS('Blocker log'!$L:$L,'Blocker log'!$A:$A,$B95,'Blocker log'!$G:$G,"Hard blocker")) -> 0 | Q95: =IF($B95="","",IF($K95<>"Complete","Assessment pending",IF($N95=0,"Ready now",VLOOKUP($P95,Lists!$D$2:$E$5,2,FALSE)))) -> Assessment pending
A96: 00170000010Dsg3AAC | B96: CompuGroup Medical SE and Co KGaA | C96: Tier 2 | D96: EMEA | E96: Germany | F96: Germany Public | G96: Cohort 1: Upgrades in progress | M96: =IF($B96="","",COUNTIFS('Blocker log'!$A:$A,$B96,'Blocker log'!$G:$G,"<>")) -> 0 | N96: =IF($B96="","",COUNTIFS('Blocker log'!$A:$A,$B96,'Blocker log'!$G:$G,"Hard blocker")) -> 0 | O96: =IF($B96="","",COUNTIFS('Blocker log'!$A:$A,$B96,'Blocker log'!$G:$G,"Hard blocker",'Blocker log'!$L:$L,9)) -> 0 | P96: =IF($B96="","",MAXIFS('Blocker log'!$L:$L,'Blocker log'!$A:$A,$B96,'Blocker log'!$G:$G,"Hard blocker")) -> 0 | Q96: =IF($B96="","",IF($K96<>"Complete","Assessment pending",IF($N96=0,"Ready now",VLOOKUP($P96,Lists!$D$2:$E$5,2,FALSE)))) -> Assessment pending
A97: 0017000001MCHlVAAX | B97: One 97 Communications Limited | C97: Tier 2 | D97: JAPAC | E97: India | F97: India Enterprise | G97: Cohort 1: Upgrades in progress | H97: 169300 | M97: =IF($B97="","",COUNTIFS('Blocker log'!$A:$A,$B97,'Blocker log'!$G:$G,"<>")) -> 0 | N97: =IF($B97="","",COUNTIFS('Blocker log'!$A:$A,$B97,'Blocker log'!$G:$G,"Hard blocker")) -> 0 | O97: =IF($B97="","",COUNTIFS('Blocker log'!$A:$A,$B97,'Blocker log'!$G:$G,"Hard blocker",'Blocker log'!$L:$L,9)) -> 0 | P97: =IF($B97="","",MAXIFS('Blocker log'!$L:$L,'Blocker log'!$A:$A,$B97,'Blocker log'!$G:$G,"Hard blocker")) -> 0 | Q97: =IF($B97="","",IF($K97<>"Complete","Assessment pending",IF($N97=0,"Ready now",VLOOKUP($P97,Lists!$D$2:$E$5,2,FALSE)))) -> Assessment pending
A98: 0017000001V6ZhvAAF | B98: Nuvei Ltd | C98: Tier 2 | D98: EMEA | E98: Israel/Greece | F98: Israel | G98: Cohort 1: Upgrades in progress | H98: 247812 | M98: =IF($B98="","",COUNTIFS('Blocker log'!$A:$A,$B98,'Blocker log'!$G:$G,"<>")) -> 0 | N98: =IF($B98="","",COUNTIFS('Blocker log'!$A:$A,$B98,'Blocker log'!$G:$G,"Hard blocker")) -> 0 | O98: =IF($B98="","",COUNTIFS('Blocker log'!$A:$A,$B98,'Blocker log'!$G:$G,"Hard blocker",'Blocker log'!$L:$L,9)) -> 0 | P98: =IF($B98="","",MAXIFS('Blocker log'!$L:$L,'Blocker log'!$A:$A,$B98,'Blocker log'!$G:$G,"Hard blocker")) -> 0 | Q98: =IF($B98="","",IF($K98<>"Complete","Assessment pending",IF($N98=0,"Ready now",VLOOKUP($P98,Lists!$D$2:$E$5,2,FALSE)))) -> Assessment pending
A99: 0017000000nyWK2AAM | B99: Mercadona | C99: Tier 2 | D99: EMEA | E99: Iberia | F99: Spain Private | G99: Cohort 1: Upgrades in progress | H99: 244200 | M99: =IF($B99="","",COUNTIFS('Blocker log'!$A:$A,$B99,'Blocker log'!$G:$G,"<>")) -> 0 | N99: =IF($B99="","",COUNTIFS('Blocker log'!$A:$A,$B99,'Blocker log'!$G:$G,"Hard blocker")) -> 0 | O99: =IF($B99="","",COUNTIFS('Blocker log'!$A:$A,$B99,'Blocker log'!$G:$G,"Hard blocker",'Blocker log'!$L:$L,9)) -> 0 | P99: =IF($B99="","",MAXIFS('Blocker log'!$L:$L,'Blocker log'!$A:$A,$B99,'Blocker log'!$G:$G,"Hard blocker")) -> 0 | Q99: =IF($B99="","",IF($K99<>"Complete","Assessment pending",IF($N99=0,"Ready now",VLOOKUP($P99,Lists!$D$2:$E$5,2,FALSE)))) -> Assessment pending
A100: 0017000000UUsrOAAT | B100: Advocate Aurora Health | C100: Tier 2 | D100: AMER | E100: AMER Strategic West | F100: AMER Strategic West Healthcare East | G100: Cohort 1: Upgrades in progress | H100: 240106 | M100: =IF($B100="","",COUNTIFS('Blocker log'!$A:$A,$B100,'Blocker log'!$G:$G,"<>")) -> 0 | N100: =IF($B100="","",COUNTIFS('Blocker log'!$A:$A,$B100,'Blocker log'!$G:$G,"Hard blocker")) -> 0 | O100: =IF($B100="","",COUNTIFS('Blocker log'!$A:$A,$B100,'Blocker log'!$G:$G,"Hard blocker",'Blocker log'!$L:$L,9)) -> 0 | P100: =IF($B100="","",MAXIFS('Blocker log'!$L:$L,'Blocker log'!$A:$A,$B100,'Blocker log'!$G:$G,"Hard blocker")) -> 0 | Q100: =IF($B100="","",IF($K100<>"Complete","Assessment pending",IF($N100=0,"Ready now",VLOOKUP($P100,Lists!$D$2:$E$5,2,FALSE)))) -> Assessment pending
...

Sheet Blocker log
A1: Account | B1: Gap | C1: Planned release | D1: Default view | E1: PM owner | F1: Telemetry signal | G1: Customer outcome | H1: Description / how they use it (scale) | I1: Workaround and who delivers it | J1: Telemetry matched customer? | K1: Sprint | L1: Release rank | M1: Escalate? | N1: Date validated | O1: Notes
A2: Example Corp (ignore this row) | B2: Audit Asset Trail | C2: {=IF($B2="","",INDEX('Gap reference'!$C$2:$C$60,MATCH($B2,'Gap reference'!$A$2:$A$60,0)))} -> #N/A | D2: {=IF($B2="","",INDEX('Gap reference'!$D$2:$D$60,MATCH($B2,'Gap reference'!$A$2:$A$60,0)))} -> #N/A | E2: {=IF($B2="","",INDEX('Gap reference'!$G$2:$G$60,MATCH($B2,'Gap reference'!$A$2:$A$60,0)))} -> #N/A | F2: Flagged | G2: Hard blocker | H2: TKG clusters run about 40% of production workloads | J2: Yes | L2: =IF($B2="","",VLOOKUP($C2,Lists!$A$2:$B$10,2,FALSE)) -> #N/A | M2: =IF(AND($G2="Hard blocker",$L2=9),"Yes","") -> #N/A | N2: 46303
A3: Example Corp (ignore this row) | B3: RQL to XQL custom rules | C3: {=IF($B3="","",INDEX('Gap reference'!$C$2:$C$60,MATCH($B3,'Gap reference'!$A$2:$A$60,0)))} -> Oct 2026 to Jan 2027 | D3: {=IF($B3="","",INDEX('Gap reference'!$D$2:$D$60,MATCH($B3,'Gap reference'!$A$2:$A$60,0)))} -> Major blocker | E3: {=IF($B3="","",INDEX('Gap reference'!$G$2:$G$60,MATCH($B3,'Gap reference'!$A$2:$A$60,0)))} -> Ashwin Manekar | F3: Flagged | G3: Workaround accepted | H3: ~120 custom rules; 15 fail translation | I3: PS rewrites the 15 failing rules before cutover | J3: Yes | L3: =IF($B3="","",VLOOKUP($C3,Lists!$A$2:$B$10,2,FALSE)) -> 2 | M3: =IF(AND($G3="Hard blocker",$L3=9),"Yes","") | N3: 46303
A4: Example Corp (ignore this row) | B4: GuardDuty ingestion | C4: {=IF($B4="","",INDEX('Gap reference'!$C$2:$C$60,MATCH($B4,'Gap reference'!$A$2:$A$60,0)))} -> Jan 2027 | D4: {=IF($B4="","",INDEX('Gap reference'!$D$2:$D$60,MATCH($B4,'Gap reference'!$A$2:$A$60,0)))} -> Validate in discovery | E4: {=IF($B4="","",INDEX('Gap reference'!$G$2:$G$60,MATCH($B4,'Gap reference'!$A$2:$A$60,0)))} -> Elad Shuster | F4: Flagged | G4: Not needed | H4: Findings duplicate Cortex Cloud detections | J4: No, flagged but not used | L4: =IF($B4="","",VLOOKUP($C4,Lists!$A$2:$B$10,2,FALSE)) -> 2 | M4: =IF(AND($G4="Hard blocker",$L4=9),"Yes","") | N4: 46303
A5: The Charles Schwab Corporation | B5: RQL to XQL custom rules | C5: {=IF($B5="","",INDEX('Gap reference'!$C$2:$C$60,MATCH($B5,'Gap reference'!$A$2:$A$60,0)))} -> Oct 2026 to Jan 2027 | D5: {=IF($B5="","",INDEX('Gap reference'!$D$2:$D$60,MATCH($B5,'Gap reference'!$A$2:$A$60,0)))} -> Major blocker | E5: {=IF($B5="","",INDEX('Gap reference'!$G$2:$G$60,MATCH($B5,'Gap reference'!$A$2:$A$60,0)))} -> Ashwin Manekar | F5: Flagged | G5: Workaround accepted | H5: 367 run policies with RQL in scope (518 total incl. 151 build). 315 translated as of Oct 22; just under 40 remaining. | I5: PS (Phelipe) translating by hand; Schwab (Ladi) correcting defects in its own RQL. | J5: Yes | L5: =IF($B5="","",VLOOKUP($C5,Lists!$A$2:$B$10,2,FALSE)) -> 2 | M5: =IF(AND($G5="Hard blocker",$L5=9),"Yes","") | N5: 46317 | O5: Telemetry counts 601 custom policies vs 518; reconciling.
A6: The Charles Schwab Corporation | B6: Terraform provider gaps | C6: {=IF($B6="","",INDEX('Gap reference'!$C$2:$C$60,MATCH($B6,'Gap reference'!$A$2:$A$60,0)))} -> Jan 2027 | D6: {=IF($B6="","",INDEX('Gap reference'!$D$2:$D$60,MATCH($B6,'Gap reference'!$A$2:$A$60,0)))} -> Major blocker | E6: {=IF($B6="","",INDEX('Gap reference'!$G$2:$G$60,MATCH($B6,'Gap reference'!$A$2:$A$60,0)))} -> Ashwin Manekar | F6: No telemetry | G6: Hard blocker | H6: Schwab manages rules, policies and compliance controls through the Terraform provider after deployment (COE 524). | J6: No telemetry | L6: =IF($B6="","",VLOOKUP($C6,Lists!$A$2:$B$10,2,FALSE)) -> 2 | N6: 46314 | O6: Production control creation failure (04248274 / XSUP-78801) routed to David as a bug.
A7: The Charles Schwab Corporation | B7: Asset audit trail | C7: {=IF($B7="","",INDEX('Gap reference'!$C$2:$C$60,MATCH($B7,'Gap reference'!$A$2:$A$60,0)))} -> H1 CY2027 (Internal) | D7: {=IF($B7="","",INDEX('Gap reference'!$D$2:$D$60,MATCH($B7,'Gap reference'!$A$2:$A$60,0)))} -> Major blocker | E7: {=IF($B7="","",INDEX('Gap reference'!$G$2:$G$60,MATCH($B7,'Gap reference'!$A$2:$A$60,0)))} -> Guy Liberman | F7: Flagged | G7: Unknown | H7: 15 asset audit trail API calls in 30 days. Ladi (Oct 22): nothing critical depends on it, from memory. | L7: =IF($B7="","",VLOOKUP($C7,Lists!$A$2:$B$10,2,FALSE)) -> #N/A | O7: Confirming with Justin; tracing the API caller.
A8: The Charles Schwab Corporation | B8: Terraform onboarding (full lifecycle) | C8: {=IF($B8="","",INDEX('Gap reference'!$C$2:$C$60,MATCH($B8,'Gap reference'!$A$2:$A$60,0)))} -> Oct 2026 | D8: {=IF($B8="","",INDEX('Gap reference'!$D$2:$D$60,MATCH($B8,'Gap reference'!$A$2:$A$60,0)))} -> Major blocker | E8: {=IF($B8="","",INDEX('Gap reference'!$G$2:$G$60,MATCH($B8,'Gap reference'!$A$2:$A$60,0)))} -> Ashwin Manekar | F8: No telemetry | G8: Unknown | H8: Schwab rejected the standard onboarding template and wants it customized; Azure service principal created through Terraform. | I8: Service principal via azuread_service_principal from the wizard app ID. | J8: No telemetry | L8: =IF($B8="","",VLOOKUP($C8,Lists!$A$2:$B$10,2,FALSE)) -> 1
A9: The Charles Schwab Corporation | B9: Jira ticketing for issues | C9: {=IF($B9="","",INDEX('Gap reference'!$C$2:$C$60,MATCH($B9,'Gap reference'!$A$2:$A$60,0)))} -> #N/A | D9: {=IF($B9="","",INDEX('Gap reference'!$D$2:$D$60,MATCH($B9,'Gap reference'!$A$2:$A$60,0)))} -> #N/A | E9: {=IF($B9="","",INDEX('Gap reference'!$G$2:$G$60,MATCH($B9,'Gap reference'!$A$2:$A$60,0)))} -> #N/A | F9: No telemetry | G9: Hard blocker | H9: Cortex Cloud issues must open Jira tickets automatically; Schwab named it an open cutover blocker. | J9: No telemetry | L9: =IF($B9="","",VLOOKUP($C9,Lists!$A$2:$B$10,2,FALSE)) -> #N/A | N9: 46311 | O9: Owner per Ashwin, Oct 23: notifications (Guy Liberman). Specifics being confirmed with Schwab.
A10: The Charles Schwab Corporation | B10: Compliance categories via API | C10: {=IF($B10="","",INDEX('Gap reference'!$C$2:$C$60,MATCH($B10,'Gap reference'!$A$2:$A$60,0)))} -> #N/A | D10: {=IF($B10="","",INDEX('Gap reference'!$D$2:$D$60,MATCH($B10,'Gap reference'!$A$2:$A$60,0)))} -> #N/A | E10: {=IF($B10="","",INDEX('Gap reference'!$G$2:$G$60,MATCH($B10,'Gap reference'!$A$2:$A$60,0)))} -> #N/A | F10: No telemetry | G10: Hard blocker | H10: Schwab builds custom compliance standards and subcategories through the API (case 04194314). | J10: No telemetry | L10: =IF($B10="","",VLOOKUP($C10,Lists!$A$2:$B$10,2,FALSE)) -> #N/A | N10: 46267 | O10: Production vs test subcategory difference routed to David as a bug.
A11: The Charles Schwab Corporation | B11: Asset groups from cloud account tags | C11: {=IF($B11="","",INDEX('Gap reference'!$C$2:$C$60,MATCH($B11,'Gap reference'!$A$2:$A$60,0)))} -> #N/A | D11: {=IF($B11="","",INDEX('Gap reference'!$D$2:$D$60,MATCH($B11,'Gap reference'!$A$2:$A$60,0)))} -> #N/A | E11: {=IF($B11="","",INDEX('Gap reference'!$G$2:$G$60,MATCH($B11,'Gap reference'!$A$2:$A$60,0)))} -> #N/A | F11: No telemetry | G11: Workaround accepted | H11: Ownership and access are organized by cloud account tags; asset groups and business applications must inherit them. | I11: PS automation (Phelipe) creates asset groups and business applications from tags. | J11: No telemetry | L11: =IF($B11="","",VLOOKUP($C11,Lists!$A$2:$B$10,2,FALSE)) -> #N/A | N11: 46315
A12: The Charles Schwab Corporation | B12: IP-in-CIDR search on firewall rules | C12: {=IF($B12="","",INDEX('Gap reference'!$C$2:$C$60,MATCH($B12,'Gap reference'!$A$2:$A$60,0)))} -> #N/A | D12: {=IF($B12="","",INDEX('Gap reference'!$D$2:$D$60,MATCH($B12,'Gap reference'!$A$2:$A$60,0)))} -> #N/A | E12: {=IF($B12="","",INDEX('Gap reference'!$G$2:$G$60,MATCH($B12,'Gap reference'!$A$2:$A$60,0)))} -> #N/A | F12: No telemetry | G12: Workaround accepted | H12: Schwab looks up every GCP firewall rule allowing a given IP; 192 VPC rules plus firewall policies. | I12: XQL lookup validated in Schwab's tenant (TSE); no automatic flagging. | J12: No telemetry | L12: =IF($B12="","",VLOOKUP($C12,Lists!$A$2:$B$10,2,FALSE)) -> #N/A | N12: 46311 | O12: XPANDR-15405
A13: The Charles Schwab Corporation | B13: GCP address group resolution | C13: {=IF($B13="","",INDEX('Gap reference'!$C$2:$C$60,MATCH($B13,'Gap reference'!$A$2:$A$60,0)))} -> #N/A | D13: {=IF($B13="","",INDEX('Gap reference'!$D$2:$D$60,MATCH($B13,'Gap reference'!$A$2:$A$60,0)))} -> #N/A | E13: {=IF($B13="","",INDEX('Gap reference'!$G$2:$G$60,MATCH($B13,'Gap reference'!$A$2:$A$60,0)))} -> #N/A | F13: No telemetry | G13: Unknown | H13: Whether Schwab's firewall policies reference address groups is not yet confirmed. | J13: No telemetry | L13: =IF($B13="","",VLOOKUP($C13,Lists!$A$2:$B$10,2,FALSE)) -> #N/A | O13: XPANDR-15404, 15401
A14: The Charles Schwab Corporation | B14: AWS audit logs without SNS | C14: {=IF($B14="","",INDEX('Gap reference'!$C$2:$C$60,MATCH($B14,'Gap reference'!$A$2:$A$60,0)))} -> #N/A | D14: {=IF($B14="","",INDEX('Gap reference'!$D$2:$D$60,MATCH($B14,'Gap reference'!$A$2:$A$60,0)))} -> #N/A | E14: {=IF($B14="","",INDEX('Gap reference'!$G$2:$G$60,MATCH($B14,'Gap reference'!$A$2:$A$60,0)))} -> #N/A | F14: No telemetry | G14: Unknown | H14: Schwab asked for EventBridge S3 event format and S3 to SQS delivery without SNS. | I14: SNS intermediary per deployment guidelines; acceptability not confirmed. | J14: No telemetry | L14: =IF($B14="","",VLOOKUP($C14,Lists!$A$2:$B$10,2,FALSE)) -> #N/A | O14: Specialist review requested Oct 5.
A15: The Charles Schwab Corporation | B15: Default policy parity | C15: {=IF($B15="","",INDEX('Gap reference'!$C$2:$C$60,MATCH($B15,'Gap reference'!$A$2:$A$60,0)))} -> #N/A | D15: {=IF($B15="","",INDEX('Gap reference'!$D$2:$D$60,MATCH($B15,'Gap reference'!$A$2:$A$60,0)))} -> #N/A | E15: {=IF($B15="","",INDEX('Gap reference'!$G$2:$G$60,MATCH($B15,'Gap reference'!$A$2:$A$60,0)))} -> #N/A | F15: No telemetry | G15: Unknown | H15: Justin asked for parity with Prisma Cloud default policies (Sep 10); scope not defined. | J15: No telemetry | L15: =IF($B15="","",VLOOKUP($C15,Lists!$A$2:$B$10,2,FALSE)) -> #N/A
A16: The Charles Schwab Corporation | B16: Image age lineage for rehydration evidence | C16: {=IF($B16="","",INDEX('Gap reference'!$C$2:$C$60,MATCH($B16,'Gap reference'!$A$2:$A$60,0)))} -> #N/A | D16: {=IF($B16="","",INDEX('Gap reference'!$D$2:$D$60,MATCH($B16,'Gap reference'!$A$2:$A$60,0)))} -> #N/A | E16: {=IF($B16="","",INDEX('Gap reference'!$G$2:$G$60,MATCH($B16,'Gap reference'!$A$2:$A$60,0)))} -> #N/A | F16: No telemetry | G16: Unknown | H16: Vulnerability management must show auditors that every workload was built from an image passed within 30 days. Prisma maps workload age to parent image age today. | J16: No telemetry | L16: =IF($B16="","",VLOOKUP($C16,Lists!$A$2:$B$10,2,FALSE)) -> #N/A | O16: Schwab mapping requirements, about two weeks (Oct 21). Rules API row (04220471) removed: bug to David.
A17: The Charles Schwab Corporation | B17: GCP Parameter Manager ingestion | C17: {=IF($B17="","",INDEX('Gap reference'!$C$2:$C$60,MATCH($B17,'Gap reference'!$A$2:$A$60,0)))} -> #N/A | D17: {=IF($B17="","",INDEX('Gap reference'!$D$2:$D$60,MATCH($B17,'Gap reference'!$A$2:$A$60,0)))} -> #N/A | E17: {=IF($B17="","",INDEX('Gap reference'!$G$2:$G$60,MATCH($B17,'Gap reference'!$A$2:$A$60,0)))} -> #N/A | F17: No telemetry | G17: Unknown | H17: Feature request (describe, list, versions) for IAM controls and audit logging; expected Nov 22. | J17: No telemetry | L17: =IF($B17="","",VLOOKUP($C17,Lists!$A$2:$B$10,2,FALSE)) -> #N/A
A18: The Charles Schwab Corporation | B18: Lambda image attributes in inventory | C18: {=IF($B18="","",INDEX('Gap reference'!$C$2:$C$60,MATCH($B18,'Gap reference'!$A$2:$A$60,0)))} -> #N/A | D18: {=IF($B18="","",INDEX('Gap reference'!$D$2:$D$60,MATCH($B18,'Gap reference'!$A$2:$A$60,0)))} -> #N/A | E18: {=IF($B18="","",INDEX('Gap reference'!$G$2:$G$60,MATCH($B18,'Gap reference'!$A$2:$A$60,0)))} -> #N/A | F18: No telemetry | G18: Unknown | H18: Feature request for Lambda image attributes such as ImageUri; expected Nov 22. | J18: No telemetry | L18: =IF($B18="","",VLOOKUP($C18,Lists!$A$2:$B$10,2,FALSE)) -> #N/A
A19: MetLife, Inc. | B19: RedHat Hardened Images Support | C19: {=IF($B19="","",INDEX('Gap reference'!$C$2:$C$60,MATCH($B19,'Gap reference'!$A$2:$A$60,0)))} -> #N/A | D19: {=IF($B19="","",INDEX('Gap reference'!$D$2:$D$60,MATCH($B19,'Gap reference'!$A$2:$A$60,0)))} -> #N/A | E19: {=IF($B19="","",INDEX('Gap reference'!$G$2:$G$60,MATCH($B19,'Gap reference'!$A$2:$A$60,0)))} -> #N/A | H19: About half of the Docker images being built and deployed by MetLife use RedHat Hardened Images as base. Current version of CortexCLI and CC Intelligence feed does not allow for complete SBOM extraction and vulnerability detection respectively.
A20: Equinix, Inc. | B20: DSPM large file set scanning w/ MIP labeling | C20: {=IF($B20="","",INDEX('Gap reference'!$C$2:$C$60,MATCH($B20,'Gap reference'!$A$2:$A$60,0)))} -> #N/A | D20: {=IF($B20="","",INDEX('Gap reference'!$D$2:$D$60,MATCH($B20,'Gap reference'!$A$2:$A$60,0)))} -> #N/A | E20: {=IF($B20="","",INDEX('Gap reference'!$G$2:$G$60,MATCH($B20,'Gap reference'!$A$2:$A$60,0)))} -> #N/A | H20: DSPM MIP Labeling and Ability to scan large number of files. Partially solved, still to be delivered and demo-ed to the customer
A21: John Hancock Financial Services, Inc. | B21: Cortex CLI: --policy-metadata-filter (policy labels) | C21: {=IF($B21="","",INDEX('Gap reference'!$C$2:$C$60,MATCH($B21,'Gap reference'!$A$2:$A$60,0)))} -> #N/A | D21: {=IF($B21="","",INDEX('Gap reference'!$D$2:$D$60,MATCH($B21,'Gap reference'!$A$2:$A$60,0)))} -> #N/A | E21: {=IF($B21="","",INDEX('Gap reference'!$G$2:$G$60,MATCH($B21,'Gap reference'!$A$2:$A$60,0)))} -> #N/A | F21: No telemetry | G21: Hard blocker | H21: Pipelines select custom YAML IaC policies by label at build time (--policy-metadata-filter policy.label). Cortex CLI lacks the flag. P0, customer-confirmed (TAC 4186899). | I21: None. DC confirmed no workaround (Oct 21). | J21: No telemetry | L21: =IF($B21="","",VLOOKUP($C21,Lists!$A$2:$B$10,2,FALSE)) -> #N/A | M21: =IF(AND($G21="Hard blocker",$L21=9),"Yes","") -> #N/A | N21: 46316 | O21: Split from the combined CLI flags row. Product list to Elad Oct 27; PM owner to be named by product.
A22: John Hancock Financial Services, Inc. | B22: End-of-life / end-of-sale package detection | C22: {=IF($B22="","",INDEX('Gap reference'!$C$2:$C$60,MATCH($B22,'Gap reference'!$A$2:$A$60,0)))} -> #N/A | D22: {=IF($B22="","",INDEX('Gap reference'!$D$2:$D$60,MATCH($B22,'Gap reference'!$A$2:$A$60,0)))} -> #N/A | E22: {=IF($B22="","",INDEX('Gap reference'!$G$2:$G$60,MATCH($B22,'Gap reference'!$A$2:$A$60,0)))} -> #N/A | F22: No telemetry | G22: Hard blocker | H22: End-of-life and end-of-sale package detection in the CWP and AppSec scanners. Customer-confirmed upgrade blocker (TAC 4186938, Asana FR). Customer vulnerability team uses Qualys for this. | I22: Prisma Cloud today: PS-built scripts. No Cortex Cloud equivalent. | J22: No telemetry | L22: =IF($B22="","",VLOOKUP($C22,Lists!$A$2:$B$10,2,FALSE)) -> #N/A | M22: =IF(AND($G22="Hard blocker",$L22=9),"Yes","") -> #N/A | N22: 46316 | O22: Routes to product through Elad (Gil Kedem scope is ADS, Outpost, CloudScan).
A23: John Hancock Financial Services, Inc. | B23: Cortex CLI finding suppression | C23: {=IF($B23="","",INDEX('Gap reference'!$C$2:$C$60,MATCH($B23,'Gap reference'!$A$2:$A$60,0)))} -> #N/A | D23: {=IF($B23="","",INDEX('Gap reference'!$D$2:$D$60,MATCH($B23,'Gap reference'!$A$2:$A$60,0)))} -> #N/A | E23: {=IF($B23="","",INDEX('Gap reference'!$G$2:$G$60,MATCH($B23,'Gap reference'!$A$2:$A$60,0)))} -> #N/A | F23: No telemetry | G23: Hard blocker | H23: Suppression of Cortex CLI findings (GitHub Action AppSec integration). Core day-to-day IaC control; customer must validate before team leave in December. Support case 04184944. | I23: Developer suppressions until Posture Policy Exception lands (support: scheduled for tenant Nov 15, field). | J23: No telemetry | L23: =IF($B23="","",VLOOKUP($C23,Lists!$A$2:$B$10,2,FALSE)) -> #N/A | M23: =IF(AND($G23="Hard blocker",$L23=9),"Yes","") -> #N/A | N23: 46316 | O23: Planned release blank until product confirms; Nov 15 is support's date (field). Validate the Suppress action seen in AppSec CI/CD Runs against this requirement.
A24: John Hancock Financial Services, Inc. | B24: Cloud onboarding via API | C24: {=IF($B24="","",INDEX('Gap reference'!$C$2:$C$60,MATCH($B24,'Gap reference'!$A$2:$A$60,0)))} -> TBC | D24: {=IF($B24="","",INDEX('Gap reference'!$D$2:$D$60,MATCH($B24,'Gap reference'!$A$2:$A$60,0)))} -> Major blocker | E24: {=IF($B24="","",INDEX('Gap reference'!$G$2:$G$60,MATCH($B24,'Gap reference'!$A$2:$A$60,0)))} -> Eyal Rotberg | F24: No telemetry | G24: Workaround accepted | H24: Manual Azure onboarding with minimal permissions, no write/action/delete (former COE 748). Customer completed phases 1 to 4 of the manual onboarding guide on Oct 21 (platform and registry roles at management group, data and KSPM roles on test subscription). | I24: Manual onboarding guide; phase 5 registration (API call) run with PS. | J24: No telemetry | L24: =IF($B24="","",VLOOKUP($C24,Lists!$A$2:$B$10,2,FALSE)) -> 9 | M24: =IF(AND($G24="Hard blocker",$L24=9),"Yes","") | N24: 46316 | O24: Supported since the September release (field, Ali). Phase 5 pending PS staffing.
A25: John Hancock Financial Services, Inc. | B25: Azure BYO Event Hub | C25: {=IF($B25="","",INDEX('Gap reference'!$C$2:$C$60,MATCH($B25,'Gap reference'!$A$2:$A$60,0)))} -> Oct 2026 | D25: {=IF($B25="","",INDEX('Gap reference'!$D$2:$D$60,MATCH($B25,'Gap reference'!$A$2:$A$60,0)))} -> Major blocker | E25: {=IF($B25="","",INDEX('Gap reference'!$G$2:$G$60,MATCH($B25,'Gap reference'!$A$2:$A$60,0)))} -> Ashwin Manekar | F25: Not flagged | G25: Unknown | H25: Customer wants audit logs from existing central Event Hubs across subscriptions; created a test Event Hub per the guide. Open: management group vs subscription activity logs; cross-subscription ingestion. | J25: No, used but not flagged | L25: =IF($B25="","",VLOOKUP($C25,Lists!$A$2:$B$10,2,FALSE)) -> 1 | M25: =IF(AND($G25="Hard blocker",$L25=9),"Yes","") | N25: 46316 | O25: Waiting on customer Event Hub diagram and PM answer (Avishai).
A26: John Hancock Financial Services, Inc. | B26: Lightweight agent | C26: {=IF($B26="","",INDEX('Gap reference'!$C$2:$C$60,MATCH($B26,'Gap reference'!$A$2:$A$60,0)))} -> Oct 2026 | D26: {=IF($B26="","",INDEX('Gap reference'!$D$2:$D$60,MATCH($B26,'Gap reference'!$A$2:$A$60,0)))} -> Major blocker | E26: {=IF($B26="","",INDEX('Gap reference'!$G$2:$G$60,MATCH($B26,'Gap reference'!$A$2:$A$60,0)))} -> Daphna Shemesh | F26: No telemetry | G26: Unknown | H26: About half of Prisma Cloud credits are on AKS; every AKS environment runs the Defender in alert mode (CIS compliance and vulnerability scanning). Customer needs a quantified XDR agent footprint for its business case (COE 749). | J26: No telemetry | L26: =IF($B26="","",VLOOKUP($C26,Lists!$A$2:$B$10,2,FALSE)) -> 1 | M26: =IF(AND($G26="Hard blocker",$L26=9),"Yes","") | N26: 46316 | O26: Plan: measure the agent on one representative AKS cluster in the test migration. Agent CWP components must be in the customer's approved software catalog to deploy at scale.
A27: John Hancock Financial Services, Inc. | B27: Other (not on gap list) | C27: {=IF($B27="","",INDEX('Gap reference'!$C$2:$C$60,MATCH($B27,'Gap reference'!$A$2:$A$60,0)))} -> #N/A | D27: {=IF($B27="","",INDEX('Gap reference'!$D$2:$D$60,MATCH($B27,'Gap reference'!$A$2:$A$60,0)))} -> #N/A | E27: {=IF($B27="","",INDEX('Gap reference'!$G$2:$G$60,MATCH($B27,'Gap reference'!$A$2:$A$60,0)))} -> #N/A | F27: No telemetry | G27: Unknown | H27: Pipeline image gating: non-compliant images must not deploy after cutover. Admission control sits in the Kubernetes connector posture management (Policy Enforcement by the Admission Controller, documented). | J27: No telemetry | L27: =IF($B27="","",VLOOKUP($C27,Lists!$A$2:$B$10,2,FALSE)) -> #N/A | M27: =IF(AND($G27="Hard blocker",$L27=9),"Yes","") -> #N/A | N27: 46316 | O27: Production gate; validate in the test migration.
A28: John Hancock Financial Services, Inc. | B28: Other (not on gap list) | C28: {=IF($B28="","",INDEX('Gap reference'!$C$2:$C$60,MATCH($B28,'Gap reference'!$A$2:$A$60,0)))} -> #N/A | D28: {=IF($B28="","",INDEX('Gap reference'!$D$2:$D$60,MATCH($B28,'Gap reference'!$A$2:$A$60,0)))} -> #N/A | E28: {=IF($B28="","",INDEX('Gap reference'!$G$2:$G$60,MATCH($B28,'Gap reference'!$A$2:$A$60,0)))} -> #N/A | F28: No telemetry | G28: Unknown | H28: Kubernetes connector host compliance scanning, and whether containerd CIS support built for the Defender carried over to the XDR agent and connector. | J28: No telemetry | L28: =IF($B28="","",VLOOKUP($C28,Lists!$A$2:$B$10,2,FALSE)) -> #N/A | M28: =IF(AND($G28="Hard blocker",$L28=9),"Yes","") -> #N/A | N28: 46316 | O28: Written question to the KSPM PM.
A29: John Hancock Financial Services, Inc. | B29: JFrog subdomains | C29: {=IF($B29="","",INDEX('Gap reference'!$C$2:$C$60,MATCH($B29,'Gap reference'!$A$2:$A$60,0)))} -> Jan 2027 | D29: {=IF($B29="","",INDEX('Gap reference'!$D$2:$D$60,MATCH($B29,'Gap reference'!$A$2:$A$60,0)))} -> Validate in discovery | E29: {=IF($B29="","",INDEX('Gap reference'!$G$2:$G$60,MATCH($B29,'Gap reference'!$A$2:$A$60,0)))} -> Elad Shuster | F29: No telemetry | G29: Unknown | H29: JFrog Artifactory self-hosted in Azure, private. Product (Avishai) confirmed CloudScan covers private ACR and JFrog; JFrog with subdomains needs admin credentials, path-based does not. | J29: No telemetry | L29: =IF($B29="","",VLOOKUP($C29,Lists!$A$2:$B$10,2,FALSE)) -> 2 | M29: =IF(AND($G29="Hard blocker",$L29=9),"Yes","") | N29: 46316 | O29: Confirm whether Manulife's JFrog uses subdomains or paths.
A30: John Hancock Financial Services, Inc. | B30: Other (not on gap list) | C30: {=IF($B30="","",INDEX('Gap reference'!$C$2:$C$60,MATCH($B30,'Gap reference'!$A$2:$A$60,0)))} -> #N/A | D30: {=IF($B30="","",INDEX('Gap reference'!$D$2:$D$60,MATCH($B30,'Gap reference'!$A$2:$A$60,0)))} -> #N/A | E30: {=IF($B30="","",INDEX('Gap reference'!$G$2:$G$60,MATCH($B30,'Gap reference'!$A$2:$A$60,0)))} -> #N/A | F30: No telemetry | G30: Unknown | H30: Evaluate policies from a local git repo (policy as code) in Cortex CLI (TAC 4186920). | J30: No telemetry | L30: =IF($B30="","",VLOOKUP($C30,Lists!$A$2:$B$10,2,FALSE)) -> #N/A | M30: =IF(AND($G30="Hard blocker",$L30=9),"Yes","") -> #N/A | O30: From account issues tracker; not yet confirmed as a blocker.
A31: John Hancock Financial Services, Inc. | B31: Other (not on gap list) | C31: {=IF($B31="","",INDEX('Gap reference'!$C$2:$C$60,MATCH($B31,'Gap reference'!$A$2:$A$60,0)))} -> #N/A | D31: {=IF($B31="","",INDEX('Gap reference'!$D$2:$D$60,MATCH($B31,'Gap reference'!$A$2:$A$60,0)))} -> #N/A | E31: {=IF($B31="","",INDEX('Gap reference'!$G$2:$G$60,MATCH($B31,'Gap reference'!$A$2:$A$60,0)))} -> #N/A | F31: No telemetry | G31: Unknown | H31: Nested Terraform module scanning (TAC 4186936; prior RFE PANWRFE-I-1429). | J31: No telemetry | L31: =IF($B31="","",VLOOKUP($C31,Lists!$A$2:$B$10,2,FALSE)) -> #N/A | M31: =IF(AND($G31="Hard blocker",$L31=9),"Yes","") -> #N/A | O31: From account issues tracker; not yet confirmed as a blocker.
A32: John Hancock Financial Services, Inc. | B32: Other (not on gap list) | C32: {=IF($B32="","",INDEX('Gap reference'!$C$2:$C$60,MATCH($B32,'Gap reference'!$A$2:$A$60,0)))} -> #N/A | D32: {=IF($B32="","",INDEX('Gap reference'!$D$2:$D$60,MATCH($B32,'Gap reference'!$A$2:$A$60,0)))} -> #N/A | E32: {=IF($B32="","",INDEX('Gap reference'!$G$2:$G$60,MATCH($B32,'Gap reference'!$A$2:$A$60,0)))} -> #N/A | F32: No telemetry | G32: Unknown | H32: Cortex CLI output shows failed checks only, not passed (TAC 4186889). | J32: No telemetry | L32: =IF($B32="","",VLOOKUP($C32,Lists!$A$2:$B$10,2,FALSE)) -> #N/A | M32: =IF(AND($G32="Hard blocker",$L32=9),"Yes","") -> #N/A | O32: From account issues tracker.
A33: John Hancock Financial Services, Inc. | B33: Other (not on gap list) | C33: {=IF($B33="","",INDEX('Gap reference'!$C$2:$C$60,MATCH($B33,'Gap reference'!$A$2:$A$60,0)))} -> #N/A | D33: {=IF($B33="","",INDEX('Gap reference'!$D$2:$D$60,MATCH($B33,'Gap reference'!$A$2:$A$60,0)))} -> #N/A | E33: {=IF($B33="","",INDEX('Gap reference'!$G$2:$G$60,MATCH($B33,'Gap reference'!$A$2:$A$60,0)))} -> #N/A | F33: No telemetry | G33: Unknown | H33: Suppress an IaC issue directly from the console link (TAC 4186880). | J33: No telemetry | L33: =IF($B33="","",VLOOKUP($C33,Lists!$A$2:$B$10,2,FALSE)) -> #N/A | M33: =IF(AND($G33="Hard blocker",$L33=9),"Yes","") -> #N/A | O33: From account issues tracker.
A34: John Hancock Financial Services, Inc. | B34: Other (not on gap list) | C34: {=IF($B34="","",INDEX('Gap reference'!$C$2:$C$60,MATCH($B34,'Gap reference'!$A$2:$A$60,0)))} -> #N/A | D34: {=IF($B34="","",INDEX('Gap reference'!$D$2:$D$60,MATCH($B34,'Gap reference'!$A$2:$A$60,0)))} -> #N/A | E34: {=IF($B34="","",INDEX('Gap reference'!$G$2:$G$60,MATCH($B34,'Gap reference'!$A$2:$A$60,0)))} -> #N/A | F34: No telemetry | G34: Unknown | H34: No dedicated results page for CWP Cortex CLI scans. | J34: No telemetry | L34: =IF($B34="","",VLOOKUP($C34,Lists!$A$2:$B$10,2,FALSE)) -> #N/A | M34: =IF(AND($G34="Hard blocker",$L34=9),"Yes","") -> #N/A | O34: From account issues tracker.
A35: John Hancock Financial Services, Inc. | B35: Other (not on gap list) | C35: {=IF($B35="","",INDEX('Gap reference'!$C$2:$C$60,MATCH($B35,'Gap reference'!$A$2:$A$60,0)))} -> #N/A | D35: {=IF($B35="","",INDEX('Gap reference'!$D$2:$D$60,MATCH($B35,'Gap reference'!$A$2:$A$60,0)))} -> #N/A | E35: {=IF($B35="","",INDEX('Gap reference'!$G$2:$G$60,MATCH($B35,'Gap reference'!$A$2:$A$60,0)))} -> #N/A | F35: No telemetry | G35: Not needed | H35: Python custom policy conversion. Customer uses YAML only for IaC policies; Python referred to planned Checkov Kubernetes config scanning, not enabled today. | J35: No telemetry | L35: =IF($B35="","",VLOOKUP($C35,Lists!$A$2:$B$10,2,FALSE)) -> #N/A | M35: =IF(AND($G35="Hard blocker",$L35=9),"Yes","") -> #N/A | N35: 46316 | O35: Future use case: Kubernetes config scanning in Cortex CLI (coverage question to AppSec PM).
A36: John Hancock Financial Services, Inc. | B36: Network anomaly detection | C36: {=IF($B36="","",INDEX('Gap reference'!$C$2:$C$60,MATCH($B36,'Gap reference'!$A$2:$A$60,0)))} -> Jan 2027 | D36: {=IF($B36="","",INDEX('Gap reference'!$D$2:$D$60,MATCH($B36,'Gap reference'!$A$2:$A$60,0)))} -> Major blocker | E36: {=IF($B36="","",INDEX('Gap reference'!$G$2:$G$60,MATCH($B36,'Gap reference'!$A$2:$A$60,0)))} -> Elad Shuster | F36: Flagged | G36: Unknown | H36: Telemetry: 43 network anomaly alerts in CDR (item: Flow logs: anomaly detection in CDR). | L36: =IF($B36="","",VLOOKUP($C36,Lists!$A$2:$B$10,2,FALSE)) -> 2 | M36: =IF(AND($G36="Hard blocker",$L36=9),"Yes","") | O36: Validate with customer.
A37: John Hancock Financial Services, Inc. | B37: CLI remediation | C37: {=IF($B37="","",INDEX('Gap reference'!$C$2:$C$60,MATCH($B37,'Gap reference'!$A$2:$A$60,0)))} -> Jan 2027 | D37: {=IF($B37="","",INDEX('Gap reference'!$D$2:$D$60,MATCH($B37,'Gap reference'!$A$2:$A$60,0)))} -> Major blocker | E37: {=IF($B37="","",INDEX('Gap reference'!$G$2:$G$60,MATCH($B37,'Gap reference'!$A$2:$A$60,0)))} -> Ashwin Manekar | F37: Flagged | G37: Unknown | H37: Telemetry: 690 CLI remediation policies (11 custom). | L37: =IF($B37="","",VLOOKUP($C37,Lists!$A$2:$B$10,2,FALSE)) -> 2 | M37: =IF(AND($G37="Hard blocker",$L37=9),"Yes","") | O37: Validate with customer.
A38: John Hancock Financial Services, Inc. | B38: Asset audit trail | C38: {=IF($B38="","",INDEX('Gap reference'!$C$2:$C$60,MATCH($B38,'Gap reference'!$A$2:$A$60,0)))} -> H1 CY2027 (Internal) | D38: {=IF($B38="","",INDEX('Gap reference'!$D$2:$D$60,MATCH($B38,'Gap reference'!$A$2:$A$60,0)))} -> Major blocker | E38: {=IF($B38="","",INDEX('Gap reference'!$G$2:$G$60,MATCH($B38,'Gap reference'!$A$2:$A$60,0)))} -> Guy Liberman | F38: Flagged | G38: Unknown | H38: Telemetry: 202 asset audit trail API calls in 30 days. | L38: =IF($B38="","",VLOOKUP($C38,Lists!$A$2:$B$10,2,FALSE)) -> #N/A | M38: =IF(AND($G38="Hard blocker",$L38=9),"Yes","") -> #N/A | O38: Validate with customer.
A39: John Hancock Financial Services, Inc. | B39: Alibaba template onboarding | C39: {=IF($B39="","",INDEX('Gap reference'!$C$2:$C$60,MATCH($B39,'Gap reference'!$A$2:$A$60,0)))} -> Jan 2027 | D39: {=IF($B39="","",INDEX('Gap reference'!$D$2:$D$60,MATCH($B39,'Gap reference'!$A$2:$A$60,0)))} -> Major blocker | E39: {=IF($B39="","",INDEX('Gap reference'!$G$2:$G$60,MATCH($B39,'Gap reference'!$A$2:$A$60,0)))} -> Ashwin Manekar | F39: Flagged | G39: Unknown | H39: Telemetry flags Alibaba usage. DC: about 5% of estate on Alibaba (China business unit, Philippines lab). | L39: =IF($B39="","",VLOOKUP($C39,Lists!$A$2:$B$10,2,FALSE)) -> 2 | M39: =IF(AND($G39="Hard blocker",$L39=9),"Yes","") | O39: Validate with customer.
A40: John Hancock Financial Services, Inc. | B40: Azure EAI | C40: {=IF($B40="","",INDEX('Gap reference'!$C$2:$C$60,MATCH($B40,'Gap reference'!$A$2:$A$60,0)))} -> Oct 2026 | D40: {=IF($B40="","",INDEX('Gap reference'!$D$2:$D$60,MATCH($B40,'Gap reference'!$A$2:$A$60,0)))} -> Major blocker | E40: {=IF($B40="","",INDEX('Gap reference'!$G$2:$G$60,MATCH($B40,'Gap reference'!$A$2:$A$60,0)))} -> Ashwin Manekar | F40: Flagged | G40: Unknown | H40: Telemetry flags EAI support for Azure. | L40: =IF($B40="","",VLOOKUP($C40,Lists!$A$2:$B$10,2,FALSE)) -> 1 | M40: =IF(AND($G40="Hard blocker",$L40=9),"Yes","") | O40: Validate with customer.
A41: John Hancock Financial Services, Inc. | B41: China regions | C41: {=IF($B41="","",INDEX('Gap reference'!$C$2:$C$60,MATCH($B41,'Gap reference'!$A$2:$A$60,0)))} -> No date | D41: {=IF($B41="","",INDEX('Gap reference'!$D$2:$D$60,MATCH($B41,'Gap reference'!$A$2:$A$60,0)))} -> Major blocker | E41: {=IF($B41="","",INDEX('Gap reference'!$G$2:$G$60,MATCH($B41,'Gap reference'!$A$2:$A$60,0)))} -> Chen Segelman | F41: Flagged | G41: Unknown | H41: Telemetry flags China coverage. DC confirmed a China business unit. | L41: =IF($B41="","",VLOOKUP($C41,Lists!$A$2:$B$10,2,FALSE)) -> 9 | M41: =IF(AND($G41="Hard blocker",$L41=9),"Yes","") | O41: Validate with customer; make no commitments.
A42: John Hancock Financial Services, Inc. | B42: RQL to XQL custom rules | C42: {=IF($B42="","",INDEX('Gap reference'!$C$2:$C$60,MATCH($B42,'Gap reference'!$A$2:$A$60,0)))} -> Oct 2026 to Jan 2027 | D42: {=IF($B42="","",INDEX('Gap reference'!$D$2:$D$60,MATCH($B42,'Gap reference'!$A$2:$A$60,0)))} -> Major blocker | E42: {=IF($B42="","",INDEX('Gap reference'!$G$2:$G$60,MATCH($B42,'Gap reference'!$A$2:$A$60,0)))} -> Ashwin Manekar | F42: Flagged | G42: Unknown | H42: Telemetry: 964 custom config policies. | L42: =IF($B42="","",VLOOKUP($C42,Lists!$A$2:$B$10,2,FALSE)) -> 2 | M42: =IF(AND($G42="Hard blocker",$L42=9),"Yes","") | O42: Validate count in translation scope with customer.
A43: John Hancock Financial Services, Inc. | B43: CIEM evidence | C43: {=IF($B43="","",INDEX('Gap reference'!$C$2:$C$60,MATCH($B43,'Gap reference'!$A$2:$A$60,0)))} -> Jan 2027 | D43: {=IF($B43="","",INDEX('Gap reference'!$D$2:$D$60,MATCH($B43,'Gap reference'!$A$2:$A$60,0)))} -> Validate in discovery | E43: {=IF($B43="","",INDEX('Gap reference'!$G$2:$G$60,MATCH($B43,'Gap reference'!$A$2:$A$60,0)))} -> Ashwin Manekar | F43: Flagged | G43: Unknown | H43: Telemetry validate item: Evidence support for CIEM. | L43: =IF($B43="","",VLOOKUP($C43,Lists!$A$2:$B$10,2,FALSE)) -> 2 | M43: =IF(AND($G43="Hard blocker",$L43=9),"Yes","") | O43: Validate with customer.
A44: Kaiser Permanente | B44: PURL namespace | C44: {=IF($B44="","",INDEX('Gap reference'!$C$2:$C$60,MATCH($B44,'Gap reference'!$A$2:$A$60,0)))} -> #N/A | D44: {=IF($B44="","",INDEX('Gap reference'!$D$2:$D$60,MATCH($B44,'Gap reference'!$A$2:$A$60,0)))} -> #N/A | E44: {=IF($B44="","",INDEX('Gap reference'!$G$2:$G$60,MATCH($B44,'Gap reference'!$A$2:$A$60,0)))} -> #N/A | F44: Flagged | G44: Hard blocker | H44: Use of pURL as a field in cortex that can sync to their workflows such as jira or snow vr | K44: Sprint 1 | N44: 46316 | O44: Pending validation
A45: Kaiser Permanente | B45: Lightweight agent | C45: {=IF($B45="","",INDEX('Gap reference'!$C$2:$C$60,MATCH($B45,'Gap reference'!$A$2:$A$60,0)))} -> Oct 2026 | D45: {=IF($B45="","",INDEX('Gap reference'!$D$2:$D$60,MATCH($B45,'Gap reference'!$A$2:$A$60,0)))} -> Major blocker | E45: {=IF($B45="","",INDEX('Gap reference'!$G$2:$G$60,MATCH($B45,'Gap reference'!$A$2:$A$60,0)))} -> Daphna Shemesh | F45: Flagged | G45: blocker | H45: Lightweight agent needed to limit resource consumption | K45: Sprint 1 | N45: 46316 | O45: Pending validation
A46: Kaiser Permanente | B46: Azure Linux 3 support | C46: {=IF($B46="","",INDEX('Gap reference'!$C$2:$C$60,MATCH($B46,'Gap reference'!$A$2:$A$60,0)))} -> #N/A | D46: {=IF($B46="","",INDEX('Gap reference'!$D$2:$D$60,MATCH($B46,'Gap reference'!$A$2:$A$60,0)))} -> #N/A | E46: {=IF($B46="","",INDEX('Gap reference'!$G$2:$G$60,MATCH($B46,'Gap reference'!$A$2:$A$60,0)))} -> #N/A | F46: Flagged | G46: blocker | H46: Azure Linux 2.0 is being deprecated from Azure and we need confirmation we will be supporting V3 | K46: Sprint 1 | N46: 46316 | O46: Pending validation
A47: John Hancock Financial Services, Inc. | B47: Cortex CLI: --skip-check wildcard (CKV*) | E47: {=IF($B47="","",INDEX('Gap reference'!$G$2:$G$60,MATCH($B47,'Gap reference'!$A$2:$A$60,0)))} -> #N/A | F47: No telemetry | G47: Hard blocker | H47: Pipelines exclude rules with --skip-check CKV*. Cortex CLI lacks the flag. P0, customer-confirmed (TAC 4186899). | I47: None. DC confirmed no workaround (Oct 21). | J47: No telemetry | N47: 46316 | O47: Split from the combined CLI flags row. Product list to Elad Oct 27.
A48: John Hancock Financial Services, Inc. | B48: Cortex CLI: EVAL_TF_PLAN_AFTER_UNKNOWN | D48: {=IF($B48="","",INDEX('Gap reference'!$D$2:$D$60,MATCH($B48,'Gap reference'!$A$2:$A$60,0)))} -> #N/A | E48: {=IF($B48="","",INDEX('Gap reference'!$G$2:$G$60,MATCH($B48,'Gap reference'!$A$2:$A$60,0)))} -> #N/A | F48: No telemetry | G48: Hard blocker | H48: Terraform plan scanning with EVAL_TF_PLAN_AFTER_UNKNOWN=true; tfplan.json scans run in the customer pipelines. Cortex CLI lacks the setting. P0, customer-confirmed (TAC 4186899). | I48: None. DC confirmed no workaround (Oct 21). | J48: No telemetry | N48: 46316 | O48: Split from the combined CLI flags row. Product list to Elad Oct 27.
A49: Gilead Sciences | B49: XDR auto deploy | C49: {=IF($B49="","",INDEX('Gap reference'!$C$2:$C$60,MATCH($B49,'Gap reference'!$A$2:$A$60,0)))} -> Jan 2027 | D49: {=IF($B49="","",INDEX('Gap reference'!$D$2:$D$60,MATCH($B49,'Gap reference'!$A$2:$A$60,0)))} -> Validate in discovery | E49: {=IF($B49="","",INDEX('Gap reference'!$G$2:$G$60,MATCH($B49,'Gap reference'!$A$2:$A$60,0)))} -> Elad Shuster | F49: No telemetry | G49: Hard blocker | J49: No telemetry | N49: 46321
A50: Gilead Sciences | B50: EKS Fargate | C50: {=IF($B50="","",INDEX('Gap reference'!$C$2:$C$60,MATCH($B50,'Gap reference'!$A$2:$A$60,0)))} -> No date | D50: {=IF($B50="","",INDEX('Gap reference'!$D$2:$D$60,MATCH($B50,'Gap reference'!$A$2:$A$60,0)))} -> Validate in discovery | E50: {=IF($B50="","",INDEX('Gap reference'!$G$2:$G$60,MATCH($B50,'Gap reference'!$A$2:$A$60,0)))} -> Daphna Shemesh | F50: No telemetry | G50: Hard blocker | J50: No telemetry | N50: 46321
C51: {=IF($B51="","",INDEX('Gap reference'!$C$2:$C$60,MATCH($B51,'Gap reference'!$A$2:$A$60,0)))} | D51: {=IF($B51="","",INDEX('Gap reference'!$D$2:$D$60,MATCH($B51,'Gap reference'!$A$2:$A$60,0)))} | E51: {=IF($B51="","",INDEX('Gap reference'!$G$2:$G$60,MATCH($B51,'Gap reference'!$A$2:$A$60,0)))}
C52: {=IF($B52="","",INDEX('Gap reference'!$C$2:$C$60,MATCH($B52,'Gap reference'!$A$2:$A$60,0)))} | D52: {=IF($B52="","",INDEX('Gap reference'!$D$2:$D$60,MATCH($B52,'Gap reference'!$A$2:$A$60,0)))} | E52: {=IF($B52="","",INDEX('Gap reference'!$G$2:$G$60,MATCH($B52,'Gap reference'!$A$2:$A$60,0)))}
C53: {=IF($B53="","",INDEX('Gap reference'!$C$2:$C$60,MATCH($B53,'Gap reference'!$A$2:$A$60,0)))} | D53: {=IF($B53="","",INDEX('Gap reference'!$D$2:$D$60,MATCH($B53,'Gap reference'!$A$2:$A$60,0)))} | E53: {=IF($B53="","",INDEX('Gap reference'!$G$2:$G$60,MATCH($B53,'Gap reference'!$A$2:$A$60,0)))}
C54: {=IF($B54="","",INDEX('Gap reference'!$C$2:$C$60,MATCH($B54,'Gap reference'!$A$2:$A$60,0)))} | D54: {=IF($B54="","",INDEX('Gap reference'!$D$2:$D$60,MATCH($B54,'Gap reference'!$A$2:$A$60,0)))} | E54: {=IF($B54="","",INDEX('Gap reference'!$G$2:$G$60,MATCH($B54,'Gap reference'!$A$2:$A$60,0)))}
C55: {=IF($B55="","",INDEX('Gap reference'!$C$2:$C$60,MATCH($B55,'Gap reference'!$A$2:$A$60,0)))} | D55: {=IF($B55="","",INDEX('Gap reference'!$D$2:$D$60,MATCH($B55,'Gap reference'!$A$2:$A$60,0)))} | E55: {=IF($B55="","",INDEX('Gap reference'!$G$2:$G$60,MATCH($B55,'Gap reference'!$A$2:$A$60,0)))}
C56: {=IF($B56="","",INDEX('Gap reference'!$C$2:$C$60,MATCH($B56,'Gap reference'!$A$2:$A$60,0)))} | D56: {=IF($B56="","",INDEX('Gap reference'!$D$2:$D$60,MATCH($B56,'Gap reference'!$A$2:$A$60,0)))} | E56: {=IF($B56="","",INDEX('Gap reference'!$G$2:$G$60,MATCH($B56,'Gap reference'!$A$2:$A$60,0)))}
C57: {=IF($B57="","",INDEX('Gap reference'!$C$2:$C$60,MATCH($B57,'Gap reference'!$A$2:$A$60,0)))} | D57: {=IF($B57="","",INDEX('Gap reference'!$D$2:$D$60,MATCH($B57,'Gap reference'!$A$2:$A$60,0)))} | E57: {=IF($B57="","",INDEX('Gap reference'!$G$2:$G$60,MATCH($B57,'Gap reference'!$A$2:$A$60,0)))}
C58: {=IF($B58="","",INDEX('Gap reference'!$C$2:$C$60,MATCH($B58,'Gap reference'!$A$2:$A$60,0)))} | D58: {=IF($B58="","",INDEX('Gap reference'!$D$2:$D$60,MATCH($B58,'Gap reference'!$A$2:$A$60,0)))} | E58: {=IF($B58="","",INDEX('Gap reference'!$G$2:$G$60,MATCH($B58,'Gap reference'!$A$2:$A$60,0)))}
C59: {=IF($B59="","",INDEX('Gap reference'!$C$2:$C$60,MATCH($B59,'Gap reference'!$A$2:$A$60,0)))} | D59: {=IF($B59="","",INDEX('Gap reference'!$D$2:$D$60,MATCH($B59,'Gap reference'!$A$2:$A$60,0)))} | E59: {=IF($B59="","",INDEX('Gap reference'!$G$2:$G$60,MATCH($B59,'Gap reference'!$A$2:$A$60,0)))}
C60: {=IF($B60="","",INDEX('Gap reference'!$C$2:$C$60,MATCH($B60,'Gap reference'!$A$2:$A$60,0)))} | D60: {=IF($B60="","",INDEX('Gap reference'!$D$2:$D$60,MATCH($B60,'Gap reference'!$A$2:$A$60,0)))} | E60: {=IF($B60="","",INDEX('Gap reference'!$G$2:$G$60,MATCH($B60,'Gap reference'!$A$2:$A$60,0)))}
C61: {=IF($B61="","",INDEX('Gap reference'!$C$2:$C$60,MATCH($B61,'Gap reference'!$A$2:$A$60,0)))} | D61: {=IF($B61="","",INDEX('Gap reference'!$D$2:$D$60,MATCH($B61,'Gap reference'!$A$2:$A$60,0)))} | E61: {=IF($B61="","",INDEX('Gap reference'!$G$2:$G$60,MATCH($B61,'Gap reference'!$A$2:$A$60,0)))}
C62: {=IF($B62="","",INDEX('Gap reference'!$C$2:$C$60,MATCH($B62,'Gap reference'!$A$2:$A$60,0)))} | D62: {=IF($B62="","",INDEX('Gap reference'!$D$2:$D$60,MATCH($B62,'Gap reference'!$A$2:$A$60,0)))} | E62: {=IF($B62="","",INDEX('Gap reference'!$G$2:$G$60,MATCH($B62,'Gap reference'!$A$2:$A$60,0)))}
... C1018: {=IF($B1018="","",INDEX('Gap reference'!$C$2:$C$60,MATCH($B1018,'Gap reference'!$A$2:$A$60,0)))} | D1018: {=IF($B1018="","",INDEX('Gap reference'!$D$2:$D$60,MATCH($B1018,'Gap reference'!$A$2:$A$60,0)))} | E1018: {=IF($B1018="","",INDEX('Gap reference'!$G$2:$G$60,MATCH($B1018,'Gap reference'!$A$2:$A$60,0)))}

Sheet Gap reference
A1: Gap | B1: Module | C1: Planned release | D1: Default view | E1: Telemetry field | F1: Question to ask the customer | G1: PM owner | H1: Release rank | I1: # accounts using | J1: # accounts with hard blocker
A2: Tanzu / PCF | B2: CWP | C2: Oct 2026 | D2: Major blocker | E2: Pending | F2: Do you protect Tanzu, TKG or PCF workloads, and what share of your workloads? | G2: Daphna Shemesh | H2: =IFERROR(VLOOKUP(C2,Lists!$A$2:$B$10,2,FALSE),9) -> 1 | I2: =COUNTIFS('Blocker log'!$B:$B,A2,'Blocker log'!$G:$G,"<>Not needed",'Blocker log'!$G:$G,"<>") -> 0 | J2: =COUNTIFS('Blocker log'!$B:$B,A2,'Blocker log'!$G:$G,"Hard blocker") -> 0
A3: Azure BYO Event Hub | B3: CSPM | C3: Oct 2026 | D3: Major blocker | E3: total_event_hub_accounts | F3: Did you onboard Azure with your own Event Hub? | G3: Ashwin Manekar | H3: =IFERROR(VLOOKUP(C3,Lists!$A$2:$B$10,2,FALSE),9) -> 1 | I3: =COUNTIFS('Blocker log'!$B:$B,A3,'Blocker log'!$G:$G,"<>Not needed",'Blocker log'!$G:$G,"<>") -> 1 | J3: =COUNTIFS('Blocker log'!$B:$B,A3,'Blocker log'!$G:$G,"Hard blocker") -> 0
A4: IBM Cloud rules (~71) | B4: CSPM | C4: Oct 2026 | D4: Major blocker | E4: IBM Usage - Telemetry | F4: Do you monitor IBM Cloud and rely on the policies Cortex Cloud lacks? | G4: Ashwin Manekar | H4: =IFERROR(VLOOKUP(C4,Lists!$A$2:$B$10,2,FALSE),9) -> 1 | I4: =COUNTIFS('Blocker log'!$B:$B,A4,'Blocker log'!$G:$G,"<>Not needed",'Blocker log'!$G:$G,"<>") -> 0 | J4: =COUNTIFS('Blocker log'!$B:$B,A4,'Blocker log'!$G:$G,"Hard blocker") -> 0
A5: Azure EAI | B5: CSPM | C5: Oct 2026 | D5: Major blocker | E5: requires_azure_eai_support | F5: Question to be defined. October reaches Prisma parity; January adds more APIs. | G5: Ashwin Manekar | H5: =IFERROR(VLOOKUP(C5,Lists!$A$2:$B$10,2,FALSE),9) -> 1 | I5: =COUNTIFS('Blocker log'!$B:$B,A5,'Blocker log'!$G:$G,"<>Not needed",'Blocker log'!$G:$G,"<>") -> 1 | J5: =COUNTIFS('Blocker log'!$B:$B,A5,'Blocker log'!$G:$G,"Hard blocker") -> 0
A6: Lightweight agent | B6: Agent | C6: Oct 2026 | D6: Major blocker | E6: None | F6: Do you run large Kubernetes estates on Defender, and will you accept the XDR agent footprint until the lightweight agent is validated? | G6: Daphna Shemesh | H6: =IFERROR(VLOOKUP(C6,Lists!$A$2:$B$10,2,FALSE),9) -> 1 | I6: =COUNTIFS('Blocker log'!$B:$B,A6,'Blocker log'!$G:$G,"<>Not needed",'Blocker log'!$G:$G,"<>") -> 2 | J6: =COUNTIFS('Blocker log'!$B:$B,A6,'Blocker log'!$G:$G,"Hard blocker") -> 0
A7: IBM Cloud onboarding | B7: Onboarding, CSPM, CWP | C7: Oct 2026 | D7: Major blocker | E7: None | F7: Which of your accounts monitor IBM Cloud today? | G7: Chen Segelman | H7: =IFERROR(VLOOKUP(C7,Lists!$A$2:$B$10,2,FALSE),9) -> 1 | I7: =COUNTIFS('Blocker log'!$B:$B,A7,'Blocker log'!$G:$G,"<>Not needed",'Blocker log'!$G:$G,"<>") -> 0 | J7: =COUNTIFS('Blocker log'!$B:$B,A7,'Blocker log'!$G:$G,"Hard blocker") -> 0
A8: Terraform onboarding (full lifecycle) | B8: CSPM | C8: Oct 2026 | D8: Major blocker | E8: None | F8: Do you manage cloud accounts with Terraform? | G8: Ashwin Manekar | H8: =IFERROR(VLOOKUP(C8,Lists!$A$2:$B$10,2,FALSE),9) -> 1 | I8: =COUNTIFS('Blocker log'!$B:$B,A8,'Blocker log'!$G:$G,"<>Not needed",'Blocker log'!$G:$G,"<>") -> 1 | J8: =COUNTIFS('Blocker log'!$B:$B,A8,'Blocker log'!$G:$G,"Hard blocker") -> 0
A9: GCP Assured Workloads | B9: Onboarding | C9: Oct 2026 | D9: Major blocker | E9: None | F9: Do you run GCP Assured Workloads? (ETA being validated, CRTX-231176) | G9: Avishai Moshka | H9: =IFERROR(VLOOKUP(C9,Lists!$A$2:$B$10,2,FALSE),9) -> 1 | I9: =COUNTIFS('Blocker log'!$B:$B,A9,'Blocker log'!$G:$G,"<>Not needed",'Blocker log'!$G:$G,"<>") -> 0 | J9: =COUNTIFS('Blocker log'!$B:$B,A9,'Blocker log'!$G:$G,"Hard blocker") -> 0
A10: ServiceNow integration | B10: AppSec | C10: Oct 2026 | D10: Major blocker | E10: None | F10: Do you send alerts to ServiceNow, and are workflows automated on them? | G10: Andrew Scott | H10: =IFERROR(VLOOKUP(C10,Lists!$A$2:$B$10,2,FALSE),9) -> 1 | I10: =COUNTIFS('Blocker log'!$B:$B,A10,'Blocker log'!$G:$G,"<>Not needed",'Blocker log'!$G:$G,"<>") -> 0 | J10: =COUNTIFS('Blocker log'!$B:$B,A10,'Blocker log'!$G:$G,"Hard blocker") -> 0
A11: Red Hat certified scanner | B11: UVEM | C11: Oct 2026 | D11: Validate in discovery | E11: Pending | F11: Do you scan OpenShift or RHEL/UBI workloads, and does a regulation require a certified scanner? | G11: Andrew Scott | H11: =IFERROR(VLOOKUP(C11,Lists!$A$2:$B$10,2,FALSE),9) -> 1 | I11: =COUNTIFS('Blocker log'!$B:$B,A11,'Blocker log'!$G:$G,"<>Not needed",'Blocker log'!$G:$G,"<>") -> 0 | J11: =COUNTIFS('Blocker log'!$B:$B,A11,'Blocker log'!$G:$G,"Hard blocker") -> 0
A12: Alma Linux | B12: CWP | C12: Oct 2026 | D12: Validate in discovery | E12: Pending | F12: Do you run Alma Linux hosts, images or containers, and what share? | G12: Elad Shuster | H12: =IFERROR(VLOOKUP(C12,Lists!$A$2:$B$10,2,FALSE),9) -> 1 | I12: =COUNTIFS('Blocker log'!$B:$B,A12,'Blocker log'!$G:$G,"<>Not needed",'Blocker log'!$G:$G,"<>") -> 0 | J12: =COUNTIFS('Blocker log'!$B:$B,A12,'Blocker log'!$G:$G,"Hard blocker") -> 0
A13: Jenkins image-scan plugin | B13: CWP | C13: Oct 2026 | D13: Validate in discovery | E13: Pending | F13: Do you scan images through the Jenkins plugin? (workaround available) | G13: Elad Shuster | H13: =IFERROR(VLOOKUP(C13,Lists!$A$2:$B$10,2,FALSE),9) -> 1 | I13: =COUNTIFS('Blocker log'!$B:$B,A13,'Blocker log'!$G:$G,"<>Not needed",'Blocker log'!$G:$G,"<>") -> 0 | J13: =COUNTIFS('Blocker log'!$B:$B,A13,'Blocker log'!$G:$G,"Hard blocker") -> 0
... A59: Azure BYO app registration | B59: Onboarding | C59: Not planned | D59: Validate in discovery | E59: None | F59: Do not raise proactively; capture if raised (more common in regulated environments). | G59: Eyal Rotberg | H59: =IFERROR(VLOOKUP(C59,Lists!$A$2:$B$10,2,FALSE),9) -> 9 | I59: =COUNTIFS('Blocker log'!$B:$B,A59,'Blocker log'!$G:$G,"<>Not needed",'Blocker log'!$G:$G,"<>") -> 0 | J59: =COUNTIFS('Blocker log'!$B:$B,A59,'Blocker log'!$G:$G,"Hard blocker") -> 0
A60: EKS Automode | B60: KSPM | C60: 46388 | E60: None | F60: Describe the blocker in the log and set the release once product confirms it. | G60: Noam | H60: =IFERROR(VLOOKUP(C60,Lists!$A$2:$B$10,2,FALSE),9) -> 9 | I60: =COUNTIFS('Blocker log'!$B:$B,A60,'Blocker log'!$G:$G,"<>Not needed",'Blocker log'!$G:$G,"<>") -> 0 | J60: =COUNTIFS('Blocker log'!$B:$B,A60,'Blocker log'!$G:$G,"Hard blocker") -> 0
A61: Jira ticketing for issues | B61: Platform | C61: TBC | D61: Major blocker | E61: None | F61: Which issues must open a Jira ticket automatically, and which fields carry over? | G61: Guy Liberman
A62: Compliance categories via API | B62: Compliance | C62: TBC | D62: Major blocker | E62: None | F62: Do you build custom compliance standards and subcategories through the API?
A63: Asset groups from cloud account tags | B63: Platform | C63: TBC | D63: Validate in discovery | E63: None | F63: Do asset groups need to inherit your cloud account tags?
A64: IP-in-CIDR search on firewall rules | B64: CSPM | C64: TBC | D64: Validate in discovery | E64: None | F64: Do you look up which firewall rules allow a given IP?
A65: GCP address group resolution | B65: CSPM | C65: TBC | D65: Validate in discovery | E65: None | F65: Do your GCP firewall policies reference address groups?
A66: AWS audit logs without SNS | B66: CDR | C66: TBC | D66: Validate in discovery | E66: None | F66: Do you need EventBridge format or S3 to SQS delivery without SNS for audit logs? | G66: Guy Liberman
A67: Default policy parity | B67: CSPM | C67: TBC | D67: Validate in discovery | E67: None | F67: Which Prisma default policies need a one-to-one equivalent at cutover?
A68: GCP Parameter Manager ingestion | B68: CSPM | C68: TBC | D68: Validate in discovery | E68: None | F68: Do you need Parameter Manager resources in inventory?
A69: Lambda image attributes in inventory | B69: CSPM | C69: TBC | D69: Validate in discovery | E69: None | F69: Do you need Lambda image attributes such as ImageUri in inventory?
A70: Image age lineage for rehydration evidence | B70: CWP | C70: TBC | D70: Major blocker | E70: None | F70: Do you evidence rehydration by inheriting a workload's age from its parent image?
A71: PURL namespace | B71: CWP | C71: Oct 2026 | D71: Validate in discovery | E71: None | F71: Are PURLs for JARs are downloaded from Maven only sufficient? | G71: Elad Shuster
A72: RedHat Hardened Images Support | B72: CWP | C72: Q3 | D72: Major blocker | G72: Elad Shuster | J72: 1
A73: DSPM large file set scanning w/ MIP labeling | B73: DSPM | C73: 46296 | D73: Major blocker | G73: Yotam Ben-Ezra
A74: Azure Linux 3 support | B74: KSPM | C74: 46327 | D74: Major blocker | E74: None | F74: Do you actively use Linux AKS? | G74: Aviel Tzarfaty

Sheet Playbook feedback
A1: Date | B1: Account | C1: TSE | D1: Feedback type | E1: What we learned | F1: Suggested change (runbook, telemetry or product) | G1: Owner | H1: Status

Sheet Lists
A1: Planned release | B1: Release rank | D1: Rank | E1: Readiness bucket | G1: Tier | H1: Upgrade status | I1: Assessment status | J1: Next step | K1: Telemetry signal | L1: Customer outcome | M1: Telemetry matched customer? | N1: Feedback type | O1: Region
A2: Oct 2026 | B2: 1 | D2: 1 | E2: After October release | G2: Tier 1 | H2: In progress | I2: Not started | J2: Continue | K2: Flagged | L2: Hard blocker | M2: Yes | N2: Telemetry correction | O2: NAM
A3: Oct 2026 to Jan 2027 | B3: 2 | D3: 2 | E3: After January release | G3: Tier 2 | H3: Not started | I3: Scheduled | J3: Pause until release | K3: Not flagged | L3: Workaround accepted | M3: No, flagged but not used | N3: New blocker | O3: LATAM
A4: Jan 2027 | B4: 2 | D4: 3 | E4: After April release or later | I4: In progress | J4: Escalate | K4: No telemetry | L4: Not needed | M4: No, used but not flagged | N4: What worked | O4: EMEA
A5: Apr 2027 | B5: 3 | D5: 9 | E5: No date | I5: Complete | L5: Unknown | M5: No telemetry | N5: What fell flat | O5: JAPAC
A6: Jul 2027 | B6: 3
A7: TBC | B7: 9
A8: No date | B8: 9
A9: Not planned | B9: 9
A10: Unknown | B10: 9
A12: Rank 2 for 'Oct 2026 to Jan 2027' plans on the later date. Ranks 9 count as no committed date.

Sheet Sheet1
A1: {=UNIQUE(Accounts!I:I)} -> TSE
A2: Alan Simpkins
A3: Alex Reshetniak
A5: Amir Chamma
A6: Brian Lewis
A7: Christopher Ley
A8: Daniel Tor
A9: Farooq Abrahem
A10: Jane Shin
A11: Khizar Karim
A12: Lauren Megrelis
A13: Lindsey Smith
A14: Muhammad Ali
... A84: Adam Hamilton
